Workbook

Sheet Cover
B2: Asset Liability Management (ALM) Model
B3: Health & Care Insurance Company
B4: Educational Prototype – Actuarial & Finance Department
B5: Valuation Date: 31 December 2024
B7: MODEL NAVIGATION
B8: 1 | C8: Assumptions | E8: Key economic & demographic assumptions
B9: 2 | C9: Liabilities | E9: Insurance liability cash flow projections
B10: 3 | C10: Assets | E10: Investment portfolio & cash flow projections
B11: 4 | C11: ALM_Analysis | E11: Duration, convexity & sensitivity analysis
B12: 5 | C12: Stress_Tests | E12: Solvency II stress scenarios
B13: 6 | C13: Dashboard | E13: Executive ALM dashboard & KPIs
B15: COLOUR CODING LEGEND
B16: Blue text, light blue fill | E16: Hardcoded input assumptions (user changeable)
B17: Black text, white fill | E17: Calculated formula cells (do not overwrite)
B18: Green text, white fill | E18: Links pulling data from another worksheet
B19: Black text, yellow fill | E19: Key assumption / cell requiring attention

Sheet Assumptions
A1: ALM MODEL – KEY ASSUMPTIONS
A3: A. ECONOMIC & MARKET ASSUMPTIONS
A4: Parameter | B4: Symbol | C4: Base Case | D4: Stress Down | E4: Stress Up | F4: Units | G4: Source / Notes
A5: Risk-Free Rate (10yr gilt) | B5: r_f | C5: 0.035 | D5: 0.015 | E5: 0.055 | F5: % p.a. | G5: Bank of England curve
A6: Credit Spread (avg portfolio) | B6: cs | C6: 0.0085 | D6: 0.018 | E6: 0.0045 | F6: % p.a. | G6: Merrill Lynch index
A7: Matching Adjustment | B7: MA | C7: 0.0062 | D7: 0.003 | E7: 0.008 | F7: % p.a. | G7: PRA approved
A8: Volatility Adjustment | B8: VA | C8: 0.002 | D8: 0.0008 | E8: 0.0035 | F8: % p.a. | G8: EIOPA published
A9: Discount Rate (BEL) | B9: r_d | C9: =C5+C7+C8 -> 0.0432 | D9: =D5+D7+D8 -> 0.0188 | E9: =E5+E7+E8 -> 0.0665 | F9: % p.a. | G9: r_f + MA + VA
A10: Inflation (RPI) | B10: π | C10: 0.025 | D10: 0.01 | E10: 0.045 | F10: % p.a. | G10: OBR forecast
A11: Inflation (CPI) | B11: π_CPI | C11: 0.022 | D11: 0.008 | E11: 0.04 | F11: % p.a. | G11: OBR forecast
A12: Healthcare Cost Inflation | B12: π_HC | C12: 0.038 | D12: 0.02 | E12: 0.06 | F12: % p.a. | G12: NHS reference costs
A13: Equity Return | B13: r_eq | C13: 0.07 | D13: 0.03 | E13: 0.1 | F13: % p.a. | G13: Long-run assumption
A14: Property Return | B14: r_prop | C14: 0.055 | D14: 0.02 | E14: 0.075 | F14: % p.a. | G14: MSCI UK Property
A16: B. DEMOGRAPHIC & ACTUARIAL ASSUMPTIONS
A17: Parameter | B17: Symbol | C17: Base Case | D17: Stress | E17: Units | F17: Notes
A18: Mortality Improvement (p.a.) | B18: MI | C18: 1.50% | D18: 0.50% | E18: % p.a. | F18: CMI 2023 model
A19: Longevity Stress | B19: LS | C19: N/A | D19: +10.0% | E19: % extra | F19: Solvency II SCR
A20: Morbidity Rate (base) | B20: q_m | C20: 2.80% | D20: 4.00% | E20: % p.a. | F20: Internal experience
A21: Lapse / Surrender Rate | B21: lapse | C21: 3.50% | D21: 6.00% | E21: % p.a. | F21: Product dependent
A22: New Business Growth | B22: g_NB | C22: 5.00% | D22: (5.00%) | E22: % p.a. | F22: Business plan
A23: Expense Inflation | B23: π_exp | C23: 4.00% | D23: 6.00% | E23: % p.a. | F23: HR & Finance
A24: Claims Frequency (Health) | B24: f_H | C24: 12.50% | D24: 18.00% | E24: % of EPs | F24: Internal stats
A25: Average Claim Size (£) | B25: S_H | C25: £2,400 | D25: £3,200 | E25: £ | F25: 2024 experience
A28: C. PORTFOLIO PARAMETERS
A29: Asset Class | B29: % Allocation | C29: Avg Yield | D29: Avg Duration (yrs) | E29: Rating (avg) | F29: Benchmark
A30: UK Government Bonds (Gilts) | B30: 0.4 | C30: 0.0385 | D30: 12.5 | E30: AAA | F30: FTSE Actuaries
A31: UK Corporate Bonds (IG) | B31: 0.3 | C31: 0.048 | D31: 8.2 | E31: A | F31: iBoxx £ Corp
A32: Infrastructure Debt | B32: 0.1 | C32: 0.054 | D32: 15 | E32: BBB+ | F32: Bespoke
A33: Equity (UK & Global) | B33: 0.08 | C33: 0.07 | D33: N/A | E33: N/A | F33: FTSE All-World
A34: Property | B34: 0.05 | C34: 0.055 | D34: N/A | E34: N/A | F34: MSCI UK
A35: Cash & Short-term | B35: 0.07 | C35: 0.051 | D35: 0.3 | E35: AAA | F35: SONIA+
A36: TOTAL | B36: =SUM(B30:B35) -> 1

Sheet Liabilities
A1: INSURANCE LIABILITIES – CASH FLOW PROJECTIONS
A3: Cash Flow Component | B3: Unit | C3: 2025 | D3: 2026 | E3: 2027 | F3: 2028 | G3: 2029 | H3: 2030 | I3: 2031 | J3: 2032 | K3: 2033 | L3: 2034 | M3: 2035 | N3: 2036 | O3: 2037 | P3: 2038 | Q3: 2039 | R3: 2040 | S3: 2041 | T3: 2042 | U3: 2043 | V3: 2044 | W3: 2045
A4: A. GROSS PREMIUM INCOME (£'000)
A5: Individual Health (PMI) | B5: In-Force Policies | C5: 520 | D5: =C5*(1+Assumptions!$C$21) -> 538.2 | E5: =D5*(1+Assumptions!$C$21) -> 557.037 | F5: =E5*(1+Assumptions!$C$21) -> 576.53329 | G5: =F5*(1+Assumptions!$C$21) -> 596.71196 | H5: =G5*(1+Assumptions!$C$21) -> 617.59688 | I5: =H5*(1+Assumptions!$C$21) -> 639.21277 | J5: =I5*(1+Assumptions!$C$21) -> 661.58522 | K5: =J5*(1+Assumptions!$C$21) -> 684.7407 | ... W5: =V5*(1+Assumptions!$C$21) -> 1034.6902
A6: Group Health Schemes | B6: Members (000s) | C6: 1260 | D6: =C6*(1+Assumptions!$C$21) -> 1304.1 | E6: =D6*(1+Assumptions!$C$21) -> 1349.7435 | F6: =E6*(1+Assumptions!$C$21) -> 1396.9845 | G6: =F6*(1+Assumptions!$C$21) -> 1445.879 | H6: =G6*(1+Assumptions!$C$21) -> 1496.4847 | I6: =H6*(1+Assumptions!$C$21) -> 1548.8617 | J6: =I6*(1+Assumptions!$C$21) -> 1603.0719 | K6: =J6*(1+Assumptions!$C$21) -> 1659.1794 | ... W6: =V6*(1+Assumptions!$C$21) -> 2507.134
A7: Long-Term Care | B7: Policies | C7: 154.5 | D7: =C7*(1+Assumptions!$C$21) -> 159.9075 | E7: =D7*(1+Assumptions!$C$21) -> 165.50426 | F7: =E7*(1+Assumptions!$C$21) -> 171.29691 | G7: =F7*(1+Assumptions!$C$21) -> 177.2923 | H7: =G7*(1+Assumptions!$C$21) -> 183.49753 | I7: =H7*(1+Assumptions!$C$21) -> 189.91995 | J7: =I7*(1+Assumptions!$C$21) -> 196.56715 | K7: =J7*(1+Assumptions!$C$21) -> 203.447 | ... W7: =V7*(1+Assumptions!$C$21) -> 307.42238
A8: Critical Illness | B8: Policies | C8: 306 | D8: =C8*(1+Assumptions!$C$21) -> 316.71 | E8: =D8*(1+Assumptions!$C$21) -> 327.79485 | F8: =E8*(1+Assumptions!$C$21) -> 339.26767 | G8: =F8*(1+Assumptions!$C$21) -> 351.14204 | H8: =G8*(1+Assumptions!$C$21) -> 363.43201 | I8: =H8*(1+Assumptions!$C$21) -> 376.15213 | J8: =I8*(1+Assumptions!$C$21) -> 389.31745 | K8: =J8*(1+Assumptions!$C$21) -> 402.94357 | ... W8: =V8*(1+Assumptions!$C$21) -> 608.87539
A9: Income Protection | B9: Policies | C9: 226.6 | D9: =C9*(1+Assumptions!$C$21) -> 234.531 | E9: =D9*(1+Assumptions!$C$21) -> 242.73959 | F9: =E9*(1+Assumptions!$C$21) -> 251.23547 | G9: =F9*(1+Assumptions!$C$21) -> 260.02871 | H9: =G9*(1+Assumptions!$C$21) -> 269.12972 | I9: =H9*(1+Assumptions!$C$21) -> 278.54926 | J9: =I9*(1+Assumptions!$C$21) -> 288.29848 | K9: =J9*(1+Assumptions!$C$21) -> 298.38893 | ... W9: =V9*(1+Assumptions!$C$21) -> 450.88616
A10: TOTAL GROSS PREMIUMS | C10: =SUM(C5:C9) -> 2467.1 | D10: =SUM(D5:D9) -> 2553.4485 | E10: =SUM(E5:E9) -> 2642.8192 | F10: =SUM(F5:F9) -> 2735.3179 | G10: =SUM(G5:G9) -> 2831.054 | H10: =SUM(H5:H9) -> 2930.1409 | I10: =SUM(I5:I9) -> 3032.6958 | J10: =SUM(J5:J9) -> 3138.8402 | ... W10: =SUM(W5:W9) -> 4909.0081
A12: B. GROSS CLAIMS INCURRED (£'000)
A13: PMI Claims (freq × severity) | B13: £'000 | C13: 280 | D13: =C13*(1+Assumptions!$C$23) -> 291.2 | E13: =D13*(1+Assumptions!$C$23) -> 302.848 | F13: =E13*(1+Assumptions!$C$23) -> 314.96192 | G13: =F13*(1+Assumptions!$C$23) -> 327.5604 | H13: =G13*(1+Assumptions!$C$23) -> 340.66281 | I13: =H13*(1+Assumptions!$C$23) -> 354.28933 | J13: =I13*(1+Assumptions!$C$23) -> 368.4609 | K13: =J13*(1+Assumptions!$C$23) -> 383.19933 | ... W13: =V13*(1+Assumptions!$C$23) -> 613.51448
A14: Group Health Claims | B14: £'000 | C14: 680 | D14: =C14*(1+Assumptions!$C$23) -> 707.2 | E14: =D14*(1+Assumptions!$C$23) -> 735.488 | F14: =E14*(1+Assumptions!$C$23) -> 764.90752 | G14: =F14*(1+Assumptions!$C$23) -> 795.50382 | H14: =G14*(1+Assumptions!$C$23) -> 827.32397 | I14: =H14*(1+Assumptions!$C$23) -> 860.41693 | J14: =I14*(1+Assumptions!$C$23) -> 894.83361 | K14: =J14*(1+Assumptions!$C$23) -> 930.62695 | ... W14: =V14*(1+Assumptions!$C$23) -> 1489.9637
A15: Long-Term Care Benefits | B15: £'000 | C15: 390 | D15: =C15*(1+Assumptions!$C$23) -> 405.6 | E15: =D15*(1+Assumptions!$C$23) -> 421.824 | F15: =E15*(1+Assumptions!$C$23) -> 438.69696 | G15: =F15*(1+Assumptions!$C$23) -> 456.24484 | H15: =G15*(1+Assumptions!$C$23) -> 474.49463 | I15: =H15*(1+Assumptions!$C$23) -> 493.47442 | J15: =I15*(1+Assumptions!$C$23) -> 513.21339 | K15: =J15*(1+Assumptions!$C$23) -> 533.74193 | ... W15: =V15*(1+Assumptions!$C$23) -> 854.53803
A16: Critical Illness Payments | B16: £'000 | C16: 120 | D16: =C16*(1+Assumptions!$C$23) -> 124.8 | E16: =D16*(1+Assumptions!$C$23) -> 129.792 | F16: =E16*(1+Assumptions!$C$23) -> 134.98368 | G16: =F16*(1+Assumptions!$C$23) -> 140.38303 | H16: =G16*(1+Assumptions!$C$23) -> 145.99835 | I16: =H16*(1+Assumptions!$C$23) -> 151.83828 | J16: =I16*(1+Assumptions!$C$23) -> 157.91181 | K16: =J16*(1+Assumptions!$C$23) -> 164.22829 | ... W16: =V16*(1+Assumptions!$C$23) -> 262.93478
A17: Income Protection Payments | B17: £'000 | C17: 110 | D17: =C17*(1+Assumptions!$C$23) -> 114.4 | E17: =D17*(1+Assumptions!$C$23) -> 118.976 | F17: =E17*(1+Assumptions!$C$23) -> 123.73504 | G17: =F17*(1+Assumptions!$C$23) -> 128.68444 | H17: =G17*(1+Assumptions!$C$23) -> 133.83182 | I17: =H17*(1+Assumptions!$C$23) -> 139.18509 | J17: =I17*(1+Assumptions!$C$23) -> 144.7525 | K17: =J17*(1+Assumptions!$C$23) -> 150.5426 | ... W17: =V17*(1+Assumptions!$C$23) -> 241.02355
A18: IBNR Provision | B18: £'000 | C18: 55 | D18: =C18*(1+Assumptions!$C$23) -> 57.2 | E18: =D18*(1+Assumptions!$C$23) -> 59.488 | F18: =E18*(1+Assumptions!$C$23) -> 61.86752 | G18: =F18*(1+Assumptions!$C$23) -> 64.342221 | H18: =G18*(1+Assumptions!$C$23) -> 66.91591 | I18: =H18*(1+Assumptions!$C$23) -> 69.592546 | J18: =I18*(1+Assumptions!$C$23) -> 72.376248 | K18: =J18*(1+Assumptions!$C$23) -> 75.271298 | ... W18: =V18*(1+Assumptions!$C$23) -> 120.51177
A19: TOTAL GROSS CLAIMS | C19: =SUM(C13:C18) -> 1635 | D19: =SUM(D13:D18) -> 1700.4 | E19: =SUM(E13:E18) -> 1768.416 | F19: =SUM(F13:F18) -> 1839.1526 | G19: =SUM(G13:G18) -> 1912.7187 | H19: =SUM(H13:H18) -> 1989.2275 | I19: =SUM(I13:I18) -> 2068.7966 | J19: =SUM(J13:J18) -> 2151.5485 | ... W19: =SUM(W13:W18) -> 3582.4863
A21: C. EXPENSES & REINSURANCE (£'000)
A22: Acquisition Costs | B22: 8% | C22: 62 | D22: =C22*(1+Assumptions!$C$27) -> 62 | E22: =D22*(1+Assumptions!$C$27) -> 62 | F22: =E22*(1+Assumptions!$C$27) -> 62 | G22: =F22*(1+Assumptions!$C$27) -> 62 | H22: =G22*(1+Assumptions!$C$27) -> 62 | I22: =H22*(1+Assumptions!$C$27) -> 62 | J22: =I22*(1+Assumptions!$C$27) -> 62 | K22: =J22*(1+Assumptions!$C$27) -> 62 | ... W22: =V22*(1+Assumptions!$C$27) -> 62
A23: Administration Expenses | B23: 4% | C23: 82 | D23: =C23*(1+Assumptions!$C$27) -> 82 | E23: =D23*(1+Assumptions!$C$27) -> 82 | F23: =E23*(1+Assumptions!$C$27) -> 82 | G23: =F23*(1+Assumptions!$C$27) -> 82 | H23: =G23*(1+Assumptions!$C$27) -> 82 | I23: =H23*(1+Assumptions!$C$27) -> 82 | J23: =I23*(1+Assumptions!$C$27) -> 82 | K23: =J23*(1+Assumptions!$C$27) -> 82 | ... W23: =V23*(1+Assumptions!$C$27) -> 82
A24: Commission | B24: 6% | C24: 47 | D24: =C24*(1+Assumptions!$C$27) -> 47 | E24: =D24*(1+Assumptions!$C$27) -> 47 | F24: =E24*(1+Assumptions!$C$27) -> 47 | G24: =F24*(1+Assumptions!$C$27) -> 47 | H24: =G24*(1+Assumptions!$C$27) -> 47 | I24: =H24*(1+Assumptions!$C$27) -> 47 | J24: =I24*(1+Assumptions!$C$27) -> 47 | K24: =J24*(1+Assumptions!$C$27) -> 47 | ... W24: =V24*(1+Assumptions!$C$27) -> 47
A25: Reinsurance Premium (ceded) | B25: 12% | C25: 185 | D25: =C25*(1+Assumptions!$C$27) -> 185 | E25: =D25*(1+Assumptions!$C$27) -> 185 | F25: =E25*(1+Assumptions!$C$27) -> 185 | G25: =F25*(1+Assumptions!$C$27) -> 185 | H25: =G25*(1+Assumptions!$C$27) -> 185 | I25: =H25*(1+Assumptions!$C$27) -> 185 | J25: =I25*(1+Assumptions!$C$27) -> 185 | K25: =J25*(1+Assumptions!$C$27) -> 185 | ... W25: =V25*(1+Assumptions!$C$27) -> 185
A27: D. NET LIABILITY CASH FLOWS (£'000)
A28: Net Claims + Expenses (Outgo) | B28: £'000 | C28: =C19+C22+C23+C24 -> 1826 | D28: =D19+D22+D23+D24 -> 1891.4 | E28: =E19+E22+E23+E24 -> 1959.416 | F28: =F19+F22+F23+F24 -> 2030.1526 | G28: =G19+G22+G23+G24 -> 2103.7187 | H28: =H19+H22+H23+H24 -> 2180.2275 | I28: =I19+I22+I23+I24 -> 2259.7966 | J28: =J19+J22+J23+J24 -> 2342.5485 | ... W28: =W19+W22+W23+W24 -> 3773.4863
A29: Undiscounted Liability CF | B29: £'000 | C29: =C28-C10 -> -641.1 | D29: =D28-D10 -> -662.0485 | E29: =E28-E10 -> -683.4032 | F29: =F28-F10 -> -705.16523 | G29: =G28-G10 -> -727.33525 | H29: =H28-H10 -> -749.91339 | I29: =I28-I10 -> -772.89922 | J29: =J28-J10 -> -796.29171 | ... W29: =W28-W10 -> -1135.5218
A30: Discount Factor (r_d) | B30: £'000 | C30: =1/(1+Assumptions!$C$9)^1 -> 0.95858896 | D30: =1/(1+Assumptions!$C$9)^2 -> 0.91889279 | E30: =1/(1+Assumptions!$C$9)^3 -> 0.88084048 | F30: =1/(1+Assumptions!$C$9)^4 -> 0.84436396 | G30: =1/(1+Assumptions!$C$9)^5 -> 0.80939796 | H30: =1/(1+Assumptions!$C$9)^6 -> 0.77587995 | I30: =1/(1+Assumptions!$C$9)^7 -> 0.74374995 | J30: =1/(1+Assumptions!$C$9)^8 -> 0.71295049 | K30: =1/(1+Assumptions!$C$9)^9 -> 0.68342647 | L30: =1/(1+Assumptions!$C$9)^10 -> 0.65512507 | M30: =1/(1+Assumptions!$C$9)^11 -> 0.62799565 | N30: =1/(1+Assumptions!$C$9)^12 -> 0.6019897 | O30: =1/(1+Assumptions!$C$9)^13 -> 0.57706068 | P30: =1/(1+Assumptions!$C$9)^14 -> 0.55316399 | Q30: =1/(1+Assumptions!$C$9)^15 -> 0.53025689 | R30: =1/(1+Assumptions!$C$9)^16 -> 0.5082984 | S30: =1/(1+Assumptions!$C$9)^17 -> 0.48724924 | T30: =1/(1+Assumptions!$C$9)^18 -> 0.46707174 | U30: =1/(1+Assumptions!$C$9)^19 -> 0.44772981 | V30: =1/(1+Assumptions!$C$9)^20 -> 0.42918885 | W30: =1/(1+Assumptions!$C$9)^21 -> 0.41141569
A31: Present Value of Liability CFs | B31: £'000 | C31: =C29*C30 -> -614.55138 | D31: =D29*D30 -> -608.35159 | E31: =E29*E30 -> -601.9692 | F31: =F29*F30 -> -595.4161 | G31: =G29*G30 -> -588.70367 | H31: =H29*H30 -> -581.84276 | I31: =I29*I30 -> -574.84376 | J31: =J29*J30 -> -567.71657 | ... W31: =W29*W30 -> -467.17147
A32: Cumulative PV (BEL) | B32: £'000 | C32: =C31 -> -614.55138 | D32: =C32+D31 -> -1222.903 | E32: =D32+E31 -> -1824.8722 | F32: =E32+F31 -> -2420.2883 | G32: =F32+G31 -> -3008.9919 | H32: =G32+H31 -> -3590.8347 | I32: =H32+I31 -> -4165.6785 | J32: =I32+J31 -> -4733.395 | K32: =J32+K31 -> -5293.8657 | ... W32: =V32+W31 -> -11422.305

Sheet Assets
A1: INVESTMENT PORTFOLIO – ASSET CASH FLOW PROJECTIONS
A3: Asset / CF Component | B3: Unit | C3: 2025 | D3: 2026 | E3: 2027 | F3: 2028 | G3: 2029 | H3: 2030 | I3: 2031 | J3: 2032 | K3: 2033 | L3: 2034 | M3: 2035 | N3: 2036 | O3: 2037 | P3: 2038 | Q3: 2039 | R3: 2040 | S3: 2041 | T3: 2042 | U3: 2043 | V3: 2044 | W3: 2045
A4: A. ASSET BOOK VALUES (£'000) – Opening Year
A5: UK Government Bonds (Gilts) | B5: £'000 | C5: 40000 | D5: =C5 -> 40000 | E5: =D5 -> 40000 | F5: =E5 -> 40000 | G5: =F5 -> 40000 | H5: =G5 -> 40000 | I5: =H5 -> 40000 | J5: =I5 -> 40000 | K5: =J5 -> 40000 | ... W5: =V5 -> 40000
A6: UK Corporate Bonds (IG) | B6: £'000 | C6: 30000 | D6: =C6 -> 30000 | E6: =D6 -> 30000 | F6: =E6 -> 30000 | G6: =F6 -> 30000 | H6: =G6 -> 30000 | I6: =H6 -> 30000 | J6: =I6 -> 30000 | K6: =J6 -> 30000 | ... W6: =V6 -> 30000
A7: Infrastructure Debt | B7: £'000 | C7: 10000 | D7: =C7 -> 10000 | E7: =D7 -> 10000 | F7: =E7 -> 10000 | G7: =F7 -> 10000 | H7: =G7 -> 10000 | I7: =H7 -> 10000 | J7: =I7 -> 10000 | K7: =J7 -> 10000 | ... W7: =V7 -> 10000
A8: Equity (UK & Global) | B8: £'000 | C8: 8000 | D8: =C8*(1+Assumptions!$C$14) -> 8440 | E8: =D8*(1+Assumptions!$C$14) -> 8904.2 | F8: =E8*(1+Assumptions!$C$14) -> 9393.931 | G8: =F8*(1+Assumptions!$C$14) -> 9910.5972 | H8: =G8*(1+Assumptions!$C$14) -> 10455.68 | I8: =H8*(1+Assumptions!$C$14) -> 11030.742 | J8: =I8*(1+Assumptions!$C$14) -> 11637.433 | K8: =J8*(1+Assumptions!$C$14) -> 12277.492 | ... W8: =V8*(1+Assumptions!$C$14) -> 23342.06
A9: Property | B9: £'000 | C9: 5000 | D9: =C9*(1+Assumptions!$C$15) -> 5000 | E9: =D9*(1+Assumptions!$C$15) -> 5000 | F9: =E9*(1+Assumptions!$C$15) -> 5000 | G9: =F9*(1+Assumptions!$C$15) -> 5000 | H9: =G9*(1+Assumptions!$C$15) -> 5000 | I9: =H9*(1+Assumptions!$C$15) -> 5000 | J9: =I9*(1+Assumptions!$C$15) -> 5000 | K9: =J9*(1+Assumptions!$C$15) -> 5000 | ... W9: =V9*(1+Assumptions!$C$15) -> 5000
A10: Cash & Short-term | B10: £'000 | C10: 7000 | D10: =C10*(1+Assumptions!$C$12) -> 7266 | E10: =D10*(1+Assumptions!$C$12) -> 7542.108 | F10: =E10*(1+Assumptions!$C$12) -> 7828.7081 | G10: =F10*(1+Assumptions!$C$12) -> 8126.199 | H10: =G10*(1+Assumptions!$C$12) -> 8434.9946 | I10: =H10*(1+Assumptions!$C$12) -> 8755.5244 | J10: =I10*(1+Assumptions!$C$12) -> 9088.2343 | K10: =J10*(1+Assumptions!$C$12) -> 9433.5872 | ... W10: =V10*(1+Assumptions!$C$12) -> 14758.598
A11: TOTAL ASSET VALUE | B11: £'000 | C11: =SUM(C5:C10) -> 100000 | D11: =SUM(D5:D10) -> 100706 | E11: =SUM(E5:E10) -> 101446.31 | F11: =SUM(F5:F10) -> 102222.64 | G11: =SUM(G5:G10) -> 103036.8 | H11: =SUM(H5:H10) -> 103890.67 | I11: =SUM(I5:I10) -> 104786.27 | J11: =SUM(J5:J10) -> 105725.67 | ... W11: =SUM(W5:W10) -> 123100.66
A13: B. INVESTMENT INCOME (£'000)
A14: Income: UK Government Bonds (Gilts) | B14: £'000 | C14: =C5*0.0385 -> 1540 | D14: =D5*0.0385 -> 1540 | E14: =E5*0.0385 -> 1540 | F14: =F5*0.0385 -> 1540 | G14: =G5*0.0385 -> 1540 | H14: =H5*0.0385 -> 1540 | I14: =I5*0.0385 -> 1540 | J14: =J5*0.0385 -> 1540 | ... W14: =W5*0.0385 -> 1540
A15: Income: UK Corporate Bonds (IG) | B15: £'000 | C15: =C6*0.048 -> 1440 | D15: =D6*0.048 -> 1440 | E15: =E6*0.048 -> 1440 | F15: =F6*0.048 -> 1440 | G15: =G6*0.048 -> 1440 | H15: =H6*0.048 -> 1440 | I15: =I6*0.048 -> 1440 | J15: =J6*0.048 -> 1440 | ... W15: =W6*0.048 -> 1440
A16: Income: Infrastructure Debt | B16: £'000 | C16: =C7*0.054 -> 540 | D16: =D7*0.054 -> 540 | E16: =E7*0.054 -> 540 | F16: =F7*0.054 -> 540 | G16: =G7*0.054 -> 540 | H16: =H7*0.054 -> 540 | I16: =I7*0.054 -> 540 | J16: =J7*0.054 -> 540 | ... W16: =W7*0.054 -> 540
A17: Income: Equity (UK & Global) | B17: £'000 | C17: =C8*0.07 -> 560 | D17: =D8*0.07 -> 590.8 | E17: =E8*0.07 -> 623.294 | F17: =F8*0.07 -> 657.57517 | G17: =G8*0.07 -> 693.7418 | H17: =H8*0.07 -> 731.8976 | I17: =I8*0.07 -> 772.15197 | J17: =J8*0.07 -> 814.62033 | ... W17: =W8*0.07 -> 1633.9442
A18: Income: Property | B18: £'000 | C18: =C9*0.055 -> 275 | D18: =D9*0.055 -> 275 | E18: =E9*0.055 -> 275 | F18: =F9*0.055 -> 275 | G18: =G9*0.055 -> 275 | H18: =H9*0.055 -> 275 | I18: =I9*0.055 -> 275 | J18: =J9*0.055 -> 275 | ... W18: =W9*0.055 -> 275
A19: Income: Cash & Short-term | B19: £'000 | C19: =C10*0.051 -> 357 | D19: =D10*0.051 -> 370.566 | E19: =E10*0.051 -> 384.64751 | F19: =F10*0.051 -> 399.26411 | G19: =G10*0.051 -> 414.43615 | H19: =H10*0.051 -> 430.18472 | I19: =I10*0.051 -> 446.53174 | J19: =J10*0.051 -> 463.49995 | ... W19: =W10*0.051 -> 752.68851
A20: TOTAL INVESTMENT INCOME | B20: £'000 | C20: =SUM(C14:C19) -> 4712 | D20: =SUM(D14:D19) -> 4756.366 | E20: =SUM(E14:E19) -> 4802.9415 | F20: =SUM(F14:F19) -> 4851.8393 | G20: =SUM(G14:G19) -> 4903.178 | H20: =SUM(H14:H19) -> 4957.0823 | I20: =SUM(I14:I19) -> 5013.6837 | J20: =SUM(J14:J19) -> 5073.1203 | ... W20: =SUM(W14:W19) -> 6181.6327
A22: C. ASSET CASH FLOWS vs LIABILITY CASH FLOWS
A23: Asset Cash Flows (Coupons) | B23: £'000 | C23: =C20 -> 4712 | D23: =D20 -> 4756.366 | E23: =E20 -> 4802.9415 | F23: =F20 -> 4851.8393 | G23: =G20 -> 4903.178 | H23: =H20 -> 4957.0823 | I23: =I20 -> 5013.6837 | J23: =J20 -> 5073.1203 | ... W23: =W20 -> 6181.6327
A24: Liability Cash Flows (Net Outgo) | B24: £'000 | C24: =Liabilities!C29 -> -641.1 | D24: =Liabilities!D29 -> -662.0485 | E24: =Liabilities!E29 -> -683.4032 | F24: =Liabilities!F29 -> -705.16523 | G24: =Liabilities!G29 -> -727.33525 | H24: =Liabilities!H29 -> -749.91339 | I24: =Liabilities!I29 -> -772.89922 | J24: =Liabilities!J29 -> -796.29171 | ... W24: =Liabilities!W29 -> -1135.5218
A25: Surplus / (Shortfall) | B25: £'000 | C25: =C23-C24 -> 5353.1 | D25: =D23-D24 -> 5418.4145 | E25: =E23-E24 -> 5486.3447 | F25: =F23-F24 -> 5557.0045 | G25: =G23-G24 -> 5630.5132 | H25: =H23-H24 -> 5706.9957 | I25: =I23-I24 -> 5786.5829 | J25: =J23-J24 -> 5869.412 | ... W25: =W23-W24 -> 7317.1545
A26: Cumulative Cash Flow Surplus | B26: £'000 | C26: =C25 -> 5353.1 | D26: =C26+D25 -> 10771.514 | E26: =D26+E25 -> 16257.859 | F26: =E26+F25 -> 21814.864 | G26: =F26+G25 -> 27445.377 | H26: =G26+H25 -> 33152.373 | I26: =H26+I25 -> 38938.956 | J26: =I26+J25 -> 44808.368 | K26: =J26+K25 -> 50763.994 | ... W26: =V26+W25 -> 130417.91

Sheet ALM_Analysis
A1: ALM ANALYSIS – DURATION, CONVEXITY & SENSITIVITY
A3: A. DURATION & CONVEXITY ANALYSIS
A4: Metric | B4: Assets | C4: Liabilities | D4: Duration Gap | E4: Interpretation
A5: Macaulay Duration (yrs) | B5: 11.8 | C5: 14.6 | D5: =C5-B5 -> 2.8 | E5: Assets shorter than liabilities
A6: Modified Duration | B6: 11.4 | C6: 14.1 | D6: =C6-B6 -> 2.7 | E6: Interest rate sensitivity measure
A7: Dollar Duration (£'000/bp) | B7: 11,400 | C7: 14,060 | D7: =C7-B7 -> 2660 | E7: PV01: £ change per 1bp rate move
A8: Convexity | B8: 92.5 | C8: 156.3 | D8: =C8-B8 -> 63.8 | E8: 2nd-order price sensitivity
A9: Weighted Avg Maturity (yrs) | B9: 10.2 | C9: 18.5 | D9: =C9-B9 -> 8.3 | E9: Maturity mismatch
A12: B. BEST ESTIMATE LIABILITY (BEL) & SOLVENCY CAPITAL
A13: Component | B13: £'000 | C13: % of Technical Provisions | D13: Notes
A14: Best Estimate Liability (BEL) | B14: 52,400 | C14: =B14/B14 -> 1 | D14: PV of future net cash outflows
A15: Risk Margin | B15: 3,620 | C15: =B15/B14 -> 0.069083969 | D15: Cost of capital approach, 6% CoC
A16: Technical Provisions (TP = BEL + RM) | B16: =B14+B15 -> 56020 | C16: =(B14+B15)/B14 -> 1.069084 | D16: Solvency II reporting basis
A17: SCR – Longevity Risk | B17: 4,180 | C17: =B17/B14 -> 0.079770992 | D17: 10% mortality improvement shock
A18: SCR – Interest Rate Risk | B18: 6,250 | C18: =B18/B14 -> 0.11927481 | D18: Duration gap × rate shock
A19: SCR – Equity Risk | B19: 1,600 | C19: =B19/B14 -> 0.030534351 | D19: 39% equity stress (Type 1)
A20: SCR – Property Risk | B20: 750 | C20: =B20/B14 -> 0.014312977 | D20: 25% property stress
A21: SCR – Spread Risk | B21: 2,100 | C21: =B21/B14 -> 0.040076336 | D21: Credit spread widening
A22: Diversification Benefit | B22: (3,580) | C22: =B22/B14 -> -0.068320611 | D22: Correlation matrix
A23: Total SCR (pre-diversification) | B23: =SUM(B17:B21) -> 0 | C23: =B23/B14 -> 0 | D23: Sum of individual SCRs
A24: Total SCR (post-diversification) | B24: =B23+B22 -> -3580 | C24: =B24/B14 -> -0.068320611 | D24: After diversification
A25: Own Funds (Eligible) | B25: 12,450 | C25: =B25/B14 -> 0.23759542 | D25: Tier 1 + Tier 2 capital
A26: Solvency II Ratio | B26: =B25/B24 -> -3.4776536 | C26: N/A | D26: Must be > 100%
A29: C. INTEREST RATE SENSITIVITY (PV01 / DV01 ANALYSIS)
A30: Rate Shock (bps) | B30: Asset PV Change (£'000) | C30: Liability PV Change (£'000) | D30: Net Surplus Change (£'000) | E30: Surplus Change (% of TP)
A31: -200 | B31: 24650 | C31: 16415 | D31: =B31-C31 -> 8235 | E31: =D31/56020 -> 0.14700107
A32: -100 | B32: 11862 | C32: 7798 | D32: =B32-C32 -> 4064 | E32: =D32/56020 -> 0.072545519
A33: -50 | B33: 5816 | C33: 3797 | D33: =B33-C33 -> 2019 | E33: =D33/56020 -> 0.0360407
A34: -25 | B34: 2879 | C34: 1873 | D34: =B34-C34 -> 1006 | E34: =D34/56020 -> 0.017957872
A35: 0 | B35: 0 | C35: 0 | D35: =B35-C35 -> 0 | E35: =D35/56020 -> 0
A36: 25 | B36: -2821 | C36: -1822 | D36: =B36-C36 -> -999 | E36: =D36/56020 -> -0.017832917
A37: 50 | B37: -5584 | C37: -3592 | D37: =B37-C37 -> -1992 | E37: =D37/56020 -> -0.035558729
A38: 100 | B38: -10938 | C38: -6979 | D38: =B38-C38 -> -3959 | E38: =D38/56020 -> -0.070671189
A39: 200 | B39: -20950 | C39: -13139 | D39: =B39-C39 -> -7811 | E39: =D39/56020 -> -0.13943235

Sheet Stress_Tests
A1: SOLVENCY II STRESS TESTS & SCENARIO ANALYSIS
A3: A. STANDARD FORMULA SCR SCENARIOS
A4: Scenario / Stress | B4: Shock Applied | C4: Impact on BEL (£'000) | D4: Impact on Assets (£'000) | E4: Net SCR (£'000) | F4: SCR as % of TP | G4: Post-Stress SCR Ratio | H4: RAG | I4: Action Required
A5: 1. Interest Rates ↑ 100bps | B5: +100bp parallel | C5: 3,200 | D5: (11,400) | E5: 8,200 | F5: 14.6% | G5: 144% | H5: GREEN | I5: Monitor duration gap
A6: 2. Interest Rates ↓ 100bps | B6: -100bp parallel | C6: (4,800) | D6: 11,400 | E6: 6,600 | F6: 11.8% | G6: 152% | H6: GREEN | I6: Review reinvestment risk
A7: 3. Longevity Stress | B7: +10% survival prob | C7: 5,240 | D7: - | E7: 5,240 | F7: 9.4% | G7: 133% | H7: AMBER | I7: Review reinsurance cover
A8: 4. Mass Lapse Event | B8: 40% immediate lapse | C8: (2,100) | D8: - | E8: 2,100 | F8: 3.7% | G8: 175% | H8: GREEN | I8: Surrender value monitoring
A9: 5. Pandemic / Morbidity | B9: Claims ×2 for 3yr | C9: 8,500 | D9: - | E9: 8,500 | F9: 15.2% | G9: 118% | H9: AMBER | I9: Pandemic re cover limits
A10: 6. Credit Spread +100bps | B10: +100bp on IG bonds | C10: - | D10: (8,500) | E10: 8,500 | F10: 15.2% | G10: 118% | H10: AMBER | I10: Credit quality controls
A11: 7. Equity Fall 39% | B11: 39% equity decline | C11: - | D11: (3,120) | E11: 3,120 | F11: 5.6% | G11: 163% | H11: GREEN | I11: Equity limit compliance
A12: 8. Property Fall 25% | B12: 25% property fall | C12: - | D12: (1,250) | E12: 1,250 | F12: 2.2% | G12: 179% | H12: GREEN | I12: Property exposure mgmt
A13: 9. Combined Stress | B13: Rates+100,Spread+50, Longevity | C13: 9,440 | D13: (14,820) | E13: 16,800 | F13: 30.0% | G13: 94% | H13: RED | I13: Immediate capital action
A14: 10. Reverse Stress | B14: What breaks the firm | C14: TBD | D14: TBD | E14: TBD | F14: TBD | G14: TBD | H14: N/A | I14: ORSA scenario modelling
A18: B. OWN RISK & SOLVENCY ASSESSMENT (ORSA) – ALM SECTION SUMMARY
A19: ALM Objective | B19: To ensure asset and liability cash flows are closely matched, minimising basis risk, interest rate risk, and liquidity risk within the firm's risk appetite.
A20: Key Risks | B20: 1. Duration mismatch (gap of 2.7 yrs) – main source of interest rate risk 2. Healthcare inflation risk – claims grow faster than asset income 3. Liquidity risk – large lapse event could require asset sales 4. Reinvestment risk – coupons reinvested at lower future rates
A21: Risk Appetite | B21: Board-approved limits: Duration gap ≤ 3 yrs; SCR ratio ≥ 120%; Solvency II ratio monitored vs 130% management buffer.
A22: Hedging Strategy | B22: Overlay: interest rate swaps to extend asset duration. LDI mandate for annuity-type liabilities. Reinsurance for longevity & pandemic tails.
A23: Monitoring | B23: Monthly ALM committee reporting. Quarterly Board Risk Committee. Annual ORSA and Internal Model validation.

Sheet Dashboard
A1: ALM EXECUTIVE DASHBOARD – HEALTH & CARE INSURANCE
A2: Valuation Date: 31 December 2024 | Prepared by: Actuarial & Finance | Status: FINAL
A4: SOLVENCY II RATIO | C4: TOTAL ASSET VALUE | E4: BEL | G4: DURATION GAP | I4: TOTAL SCR | K4: RISK MARGIN
A5: =ALM_Analysis!B26 -> -3.4776536 | C5: =ALM_Analysis!B25 -> 12,450 | E5: =ALM_Analysis!B14 -> 52,400 | G5: =ALM_Analysis!D5 -> 2.8 | I5: =ALM_Analysis!B24 -> -3580 | K5: =ALM_Analysis!B15 -> 3,620
A6: TARGET: ≥ 130% | C6: (£'000) | E6: Best Estimate Liability | G6: Asset – Liability | I6: Post-diversification | K6: (£'000)
A8: KEY ALM METRICS | G8: STRESS TEST OUTCOMES
A9: Metric | B9: Value | C9: Target/Limit | D9: Status | E9: Trend | F9: Action | G9: Stress Scenario | H9: Post-Stress Ratio | I9: Change | J9: Surplus/(Def) £k | K9: RAG | L9: Priority
A10: Solvency II Ratio | B10: 144% | C10: ≥ 130% | D10: GREEN | E10: ↑ | F10: Within appetite | G10: Rates +100bps | H10: 144% | I10: -0% | J10: £250 | K10: GREEN | L10: Low
A11: Duration Gap (yrs) | B11: 2.7 | C11: ≤ 3.0 | D11: GREEN | E11: → | F11: Monitor swap overlay | G11: Rates -100bps | H11: 152% | I11: +8% | J11: £870 | K11: GREEN | L11: Low
A12: Liquidity Coverage | B12: 158% | C12: ≥ 100% | D12: GREEN | E12: ↑ | F12: Comfortable | G12: Longevity +10% | H12: 133% | I12: -11% | J12: (£620) | K12: AMBER | L12: Medium
A13: PV01 (£k/bp) | B13: £2,660 | C13: < £5,000 | D13: GREEN | E13: → | F13: Within Board limit | G13: Pandemic x2 | H13: 118% | I13: -26% | J13: (£3,100) | K13: AMBER | L13: High
A14: Matching Adjustment | B14: 62bps | C14: ≥ 50bps | D14: GREEN | E14: ↓ | F14: Review MA portfolio | G14: Spread +100bps | H14: 118% | I14: -26% | J14: (£3,100) | K14: AMBER | L14: High
A15: Reinvestment Risk | B15: AMBER | C15: GREEN | D15: AMBER | E15: ↓ | F15: Extend asset duration | G15: Combined Stress | H15: 94% | I15: -50% | J15: (£7,200) | K15: RED | L15: Critical
A16: Longevity Hedge Ratio | B16: 65% | C16: ≥ 75% | D16: AMBER | E16: ↓ | F16: Buy more longevity swaps | G16: Mass Lapse 40% | H16: 175% | I16: +31% | J16: £3,300 | K16: GREEN | L16: Low
A17: Credit Quality (avg) | B17: A- | C17: ≥ BBB+ | D17: GREEN | E17: → | F17: Within guidelines | G17: Equity -39% | H17: 163% | I17: +19% | J17: £2,100 | K17: GREEN | L17: Low
A20: ASSET ALLOCATION SUMMARY | G20: ALM ACTION LOG
A21: Asset Class | B21: Market Value (£k) | C21: % Alloc | D21: Yield | E21: Duration | F21: vs Benchmark | G21: Action Item | H21: Owner | I21: Due Date | J21: Priority | K21: Status | L21: Notes
A22: UK Gilts | B22: 40,000 | C22: 40.0% | D22: 3.85% | E22: 12.5 | F22: On target | G22: Extend asset duration via IRS | H22: Treasury | I22: Jan-25 | J22: HIGH | K22: IN PROGRESS | L22: Close 2.7yr gap to <2yrs
A23: IG Corporate | B23: 30,000 | C23: 30.0% | D23: 4.80% | E23: 8.2 | F23: Slightly short | G23: Increase longevity hedge to 75% | H23: Actuarial | I23: Mar-25 | J23: HIGH | K23: PLANNED | L23: Negotiate longevity swap
A24: Infrastructure | B24: 10,000 | C24: 10.0% | D24: 5.40% | E24: 15.0 | F24: On target | G24: Review MA portfolio eligibility | H24: Finance | I24: Feb-25 | J24: MED | K24: PLANNED | L24: Ensure PRA compliance
A25: Equity | B25: 8,000 | C25: 8.0% | D25: 7.00% | E25: N/A | F25: Overweight | G25: Pandemic reinsurance renewal | H25: Risk | I25: Apr-25 | J25: HIGH | K25: OPEN | L25: Review cover limits post-ORSA
A26: Property | B26: 5,000 | C26: 5.0% | D26: 5.50% | E26: N/A | F26: On target | G26: ALM stress test update | H26: Actuarial | I26: Dec-24 | J26: MED | K26: COMPLETE | L26: Q4 2024 results filed
A27: Cash | B27: 7,000 | C27: 7.0% | D27: 5.10% | E27: 0.3 | F27: On target | G27: Credit quality review | H27: Treasury | I27: Mar-25 | J27: LOW | K27: PLANNED | L27: BBB holdings <5% limit
A28: TOTAL | B28: 100,000 | C28: 100% | D28: 4.71% | E28: 11.8 | G28: ORSA sign-off | H28: CRO | I28: Jan-25 | J28: HIGH | K28: IN PROGRESS | L28: Board pack preparation
G29: Liquidity contingency plan | H29: Finance | I29: Feb-25 | J29: MED | K29: PLANNED | L29: 1-month survival horizon
G30: Model validation – LDI | H30: Actuarial | I30: Jun-25 | J30: MED | K30: PLANNED | L30: Annual model governance
