Workbook

Sheet Overview
B1: MODEL OFFICE PROJECTION – SA1 / SP1 ACTUARIAL STUDY AID
B3: What is a Model Office?
B4: A Model Office is a full actuarial projection model that combines: (1) NEW BUSINESS MODEL – projects cashflows from all future new business (2) EXISTING BUSINESS MODEL – projects cashflows from the current in-force book Together these give management a forward-looking view of profitability, solvency, embedded value, and capital requirements (SP1 Ch11).
B10: Four Model Types (SP1 Ch11, Section 1.1)
B11: 1. Single Policy Profit Test | C11: Projects one representative policy's cashflows. Used in pricing to check the premium satisfies the profit criterion. | D11: Assumptions tab
B12: 2. New Business Model | C12: Projects cashflows from all new policies expected to be sold in future years. | D12: New Business tab
B13: 3. Existing Business Model | C13: Projects cashflows from the current in-force portfolio, running off over time. | D13: Existing Business tab
B14: 4. Full Model Office | C14: Sum of (2) and (3). Gives the complete forward-looking picture. | D14: Model Office tab
B16: Key Actuarial Concepts used in this model
B17: Model Point | C17: A representative policy record (age, benefit, term) fed into the model to stand in for a group of similar policies.
B18: Risk Discount Rate | C18: The return required by shareholders used to discount future cashflows in the profit test.
B19: Embedded Value | C19: PV of future profits from existing business + value of net assets. Increased/decreased by new business written each year.
B20: Sensitivity Test | C20: Re-running the model with a parameter varied (e.g., +10% claims) to assess vulnerability.
B21: Capital Strain | C21: Shortfall on day 1 when reserves + SCR exceed the first premium received; funded from the insurer's capital.

Sheet Assumptions
B1: ASSUMPTIONS – SINGLE POLICY PROFIT TEST & MODEL OFFICE
B3: Product Characteristics (Critical Illness, 10-year term)
B4: Sum Assured (£) | C4: 5000 | D4: Lump-sum benefit paid on CI diagnosis
B5: Annual Gross Premium (£) | C5: 600 | D5: Level annual premium paid monthly
B6: Policy Term (years) | C6: 10 | D6: Fixed benefit term
B7: Deferred Period (months) | C7: 0 | D7: No deferred period for CI
B9: Demographic Assumptions
B10: Annual CI Incidence Rate (%) | C10: 0.005 | D10: Probability of a new CI claim per policy year
B11: Annual Mortality Rate (%) | C11: 0.002 | D11: Probability of death per policy year (non-CI)
B12: Annual Lapse Rate (%) | C12: 0.07 | D12: Probability of policy lapsing per year
B13: Claims Inflation (%pa) | C13: 0.02 | D13: Future increase in claims cost (SP1 Ch13)
B15: Financial Assumptions
B16: Investment Return (%pa) | C16: 0.04 | D16: Rate earned on reserves & cashflows
B17: Risk Discount Rate (%pa) | C17: 0.08 | D17: Shareholder required return; used to PV profits
B18: Initial Expense per Policy (£) | C18: 250 | D18: Underwriting, admin at policy inception
B19: Annual Renewal Expense (£) | C19: 50 | D19: Per-policy admin cost per year
B20: Commission – Year 1 (%prem) | C20: 0.15 | D20: First-year commission to distributor
B21: Commission – Renewal (%prem) | C21: 0.05 | D21: Ongoing commission
B22: Tax Rate (%) | C22: 0.19 | D22: Corporation tax on profit
B24: Reserve Basis
B25: Reserving Incidence Rate (%) | C25: 0.006 | D25: Prudent: higher than pricing basis (SP1 Ch13)
B26: Reserve Discount Rate (%pa) | C26: 0.03 | D26: Prudent: lower than investment return
B28: Note: Blue cells = user inputs (change to run scenarios). Formulas auto-update.

Sheet Single Policy Profit Test
B1: SINGLE POLICY PROFIT TEST – One Representative CI Policy
B3: Projects cashflows for a single model-point policy over its 10-year term. The NPV of profit, discounted at the risk discount rate, shows whether the product is profitable.
B5: Item | C5: Year 1 | D5: Year 2 | E5: Year 3 | F5: Year 4 | G5: Year 5 | H5: Year 6 | I5: Year 7 | J5: Year 8 | K5: Year 9 | L5: Year 10 | M5: Total / NPV
B6: Policies In-Force (start of year) | C6: =1 -> 1 | D6: =C6*(1-Assumptions!C11)*(1-Assumptions!C12)*(1-Assumptions!C10) -> 0.9234993 | E6: =D6*(1-Assumptions!C11)*(1-Assumptions!C12)*(1-Assumptions!C10) -> 0.85285096 | F6: =E6*(1-Assumptions!C11)*(1-Assumptions!C12)*(1-Assumptions!C10) -> 0.78760726 | G6: =F6*(1-Assumptions!C11)*(1-Assumptions!C12)*(1-Assumptions!C10) -> 0.72735476 | H6: =G6*(1-Assumptions!C11)*(1-Assumptions!C12)*(1-Assumptions!C10) -> 0.67171161 | I6: =H6*(1-Assumptions!C11)*(1-Assumptions!C12)*(1-Assumptions!C10) -> 0.6203252 | J6: =I6*(1-Assumptions!C11)*(1-Assumptions!C12)*(1-Assumptions!C10) -> 0.57286989 | K6: =J6*(1-Assumptions!C11)*(1-Assumptions!C12)*(1-Assumptions!C10) -> 0.52904494 | L6: =K6*(1-Assumptions!C11)*(1-Assumptions!C12)*(1-Assumptions!C10) -> 0.48857263
B7: (+) Gross Premium Income | C7: =C6*Assumptions!C5 -> 600 | D7: =D6*Assumptions!C5 -> 554.09958 | E7: =E6*Assumptions!C5 -> 511.71057 | F7: =F6*Assumptions!C5 -> 472.56436 | G7: =G6*Assumptions!C5 -> 436.41285 | H7: =H6*Assumptions!C5 -> 403.02696 | I7: =I6*Assumptions!C5 -> 372.19512 | J7: =J6*Assumptions!C5 -> 343.72193 | K7: =K6*Assumptions!C5 -> 317.42696 | L7: =L6*Assumptions!C5 -> 293.14358 | M7: =SUM(C7:L7) -> 4304.3019
B8: (+) Investment Income | C8: =C6*Assumptions!C5*Assumptions!C16/2 -> 12 | D8: =D6*Assumptions!C5*Assumptions!C16/2 -> 11.081992 | E8: =E6*Assumptions!C5*Assumptions!C16/2 -> 10.234211 | F8: =F6*Assumptions!C5*Assumptions!C16/2 -> 9.4512871 | G8: =G6*Assumptions!C5*Assumptions!C16/2 -> 8.7282571 | H8: =H6*Assumptions!C5*Assumptions!C16/2 -> 8.0605393 | I8: =I6*Assumptions!C5*Assumptions!C16/2 -> 7.4439024 | J8: =J6*Assumptions!C5*Assumptions!C16/2 -> 6.8744386 | K8: =K6*Assumptions!C5*Assumptions!C16/2 -> 6.3485393 | L8: =L6*Assumptions!C5*Assumptions!C16/2 -> 5.8628716 | M8: =SUM(C8:L8) -> 86.086038
B9: (–) Initial Expenses | C9: =C6*Assumptions!C18 -> 250 | D9: =0 -> 0 | E9: =0 -> 0 | F9: =0 -> 0 | G9: =0 -> 0 | H9: =0 -> 0 | I9: =0 -> 0 | J9: =0 -> 0 | K9: =0 -> 0 | L9: =0 -> 0 | M9: =SUM(C9:L9) -> 250
B10: (–) Commission | C10: =C7*IF(1=1,Assumptions!C20,Assumptions!C21) -> 90 | D10: =D7*IF(2=1,Assumptions!C20,Assumptions!C21) -> 27.704979 | E10: =E7*IF(3=1,Assumptions!C20,Assumptions!C21) -> 25.585529 | F10: =F7*IF(4=1,Assumptions!C20,Assumptions!C21) -> 23.628218 | G10: =G7*IF(5=1,Assumptions!C20,Assumptions!C21) -> 21.820643 | H10: =H7*IF(6=1,Assumptions!C20,Assumptions!C21) -> 20.151348 | I10: =I7*IF(7=1,Assumptions!C20,Assumptions!C21) -> 18.609756 | J10: =J7*IF(8=1,Assumptions!C20,Assumptions!C21) -> 17.186097 | K10: =K7*IF(9=1,Assumptions!C20,Assumptions!C21) -> 15.871348 | L10: =L7*IF(10=1,Assumptions!C20,Assumptions!C21) -> 14.657179 | M10: =SUM(C10:L10) -> 275.2151
B11: (–) Claims Paid | C11: =C6*Assumptions!C10*Assumptions!C4*(1+Assumptions!C13)^(1-1) -> 25 | D11: =D6*Assumptions!C10*Assumptions!C4*(1+Assumptions!C13)^(2-1) -> 23.549232 | E11: =E6*Assumptions!C10*Assumptions!C4*(1+Assumptions!C13)^(3-1) -> 22.182653 | F11: =F6*Assumptions!C10*Assumptions!C4*(1+Assumptions!C13)^(4-1) -> 20.895378 | G11: =G6*Assumptions!C10*Assumptions!C4*(1+Assumptions!C13)^(5-1) -> 19.682804 | H11: =H6*Assumptions!C10*Assumptions!C4*(1+Assumptions!C13)^(6-1) -> 18.540597 | I11: =I6*Assumptions!C10*Assumptions!C4*(1+Assumptions!C13)^(7-1) -> 17.464673 | J11: =J6*Assumptions!C10*Assumptions!C4*(1+Assumptions!C13)^(8-1) -> 16.451186 | K11: =K6*Assumptions!C10*Assumptions!C4*(1+Assumptions!C13)^(9-1) -> 15.496512 | L11: =L6*Assumptions!C10*Assumptions!C4*(1+Assumptions!C13)^(10-1) -> 14.597238 | M11: =SUM(C11:L11) -> 193.86027
B12: (–) Renewal Expenses | C12: =0 -> 0 | D12: =D6*Assumptions!C19 -> 46.174965 | E12: =E6*Assumptions!C19 -> 42.642548 | F12: =F6*Assumptions!C19 -> 39.380363 | G12: =G6*Assumptions!C19 -> 36.367738 | H12: =H6*Assumptions!C19 -> 33.58558 | I12: =I6*Assumptions!C19 -> 31.01626 | J12: =J6*Assumptions!C19 -> 28.643494 | K12: =K6*Assumptions!C19 -> 26.452247 | L12: =L6*Assumptions!C19 -> 24.428632 | M12: =SUM(C12:L12) -> 308.69183
B13: (–) Increase in Reserves | C13: =C6*Assumptions!C25*Assumptions!C4*9/(1+Assumptions!C26)-IF(1>1,B6*(1-Assumptions!C11)*(1-Assumptions!C12)*(1-Assumptions!C10)*Assumptions!C25*Assumptions!C4*(9+1)/(1+Assumptions!C26),0) -> 262.13592 | D13: =D6*Assumptions!C25*Assumptions!C4*8/(1+Assumptions!C26)-IF(2>1,C6*(1-Assumptions!C11)*(1-Assumptions!C12)*(1-Assumptions!C10)*Assumptions!C25*Assumptions!C4*(8+1)/(1+Assumptions!C26),0) -> -26.898038 | E13: =E6*Assumptions!C25*Assumptions!C4*7/(1+Assumptions!C26)-IF(3>1,D6*(1-Assumptions!C11)*(1-Assumptions!C12)*(1-Assumptions!C10)*Assumptions!C25*Assumptions!C4*(7+1)/(1+Assumptions!C26),0) -> -24.840319 | F13: =F6*Assumptions!C25*Assumptions!C4*6/(1+Assumptions!C26)-IF(4>1,E6*(1-Assumptions!C11)*(1-Assumptions!C12)*(1-Assumptions!C10)*Assumptions!C25*Assumptions!C4*(6+1)/(1+Assumptions!C26),0) -> -22.940017 | G13: =G6*Assumptions!C25*Assumptions!C4*5/(1+Assumptions!C26)-IF(5>1,F6*(1-Assumptions!C11)*(1-Assumptions!C12)*(1-Assumptions!C10)*Assumptions!C25*Assumptions!C4*(5+1)/(1+Assumptions!C26),0) -> -21.18509 | H13: =H6*Assumptions!C25*Assumptions!C4*4/(1+Assumptions!C26)-IF(6>1,G6*(1-Assumptions!C11)*(1-Assumptions!C12)*(1-Assumptions!C10)*Assumptions!C25*Assumptions!C4*(4+1)/(1+Assumptions!C26),0) -> -19.564416 | I13: =I6*Assumptions!C25*Assumptions!C4*3/(1+Assumptions!C26)-IF(7>1,H6*(1-Assumptions!C11)*(1-Assumptions!C12)*(1-Assumptions!C10)*Assumptions!C25*Assumptions!C4*(3+1)/(1+Assumptions!C26),0) -> -18.067724 | J13: =J6*Assumptions!C25*Assumptions!C4*2/(1+Assumptions!C26)-IF(8>1,I6*(1-Assumptions!C11)*(1-Assumptions!C12)*(1-Assumptions!C10)*Assumptions!C25*Assumptions!C4*(2+1)/(1+Assumptions!C26),0) -> -16.685531 | K13: =K6*Assumptions!C25*Assumptions!C4*1/(1+Assumptions!C26)-IF(9>1,J6*(1-Assumptions!C11)*(1-Assumptions!C12)*(1-Assumptions!C10)*Assumptions!C25*Assumptions!C4*(1+1)/(1+Assumptions!C26),0) -> -15.409076 | L13: =-(K6*(1-Assumptions!C11)*(1-Assumptions!C12)*(1-Assumptions!C10)*Assumptions!C25*Assumptions!C4*1/(1+Assumptions!C26)) -> -14.230271 | M13: =SUM(C13:L13) -> 82.315441
B14: Pre-Tax Profit | C14: =C7+C8-C9-C10-C11-C12-C13 -> -15.135922 | D14: =D7+D8-D9-D10-D11-D12-D13 -> 494.65043 | E14: =E7+E8-E9-E10-E11-E12-E13 -> 456.37437 | F14: =F7+F8-F9-F10-F11-F12-F13 -> 421.0517 | G14: =G7+G8-G9-G10-G11-G12-G13 -> 388.45502 | H14: =H7+H8-H9-H10-H11-H12-H13 -> 358.37439 | I14: =I7+I8-I9-I10-I11-I12-I13 -> 330.61606 | J14: =J7+J8-J9-J10-J11-J12-J13 -> 305.00112 | ... L14: =L7+L8-L9-L10-L11-L12-L13 -> 259.55367 | M14: =SUM(C14:L14) -> 3280.3053
B15: (–) Tax | C15: =MAX(0,C14)*Assumptions!C22 -> 0 | D15: =MAX(0,D14)*Assumptions!C22 -> 93.983582 | E15: =MAX(0,E14)*Assumptions!C22 -> 86.711131 | F15: =MAX(0,F14)*Assumptions!C22 -> 79.999823 | G15: =MAX(0,G14)*Assumptions!C22 -> 73.806453 | H15: =MAX(0,H14)*Assumptions!C22 -> 68.091135 | I15: =MAX(0,I14)*Assumptions!C22 -> 62.817051 | J15: =MAX(0,J14)*Assumptions!C22 -> 57.950214 | K15: =MAX(0,K14)*Assumptions!C22 -> 53.45925 | L15: =MAX(0,L14)*Assumptions!C22 -> 49.315198 | M15: =SUM(C15:L15) -> 626.13384
B16: Post-Tax Profit | C16: =C14-C15 -> -15.135922 | D16: =D14-D15 -> 400.66685 | E16: =E14-E15 -> 369.66324 | F16: =F14-F15 -> 341.05188 | G16: =G14-G15 -> 314.64856 | H16: =H14-H15 -> 290.28326 | I16: =I14-I15 -> 267.79901 | J16: =J14-J15 -> 247.05091 | ... L16: =L14-L15 -> 210.23847 | M16: =SUM(C16:L16) -> 2654.1715
B17: Discounted Profit (PV @ RDR) | C17: =C16/(1+Assumptions!C17)^1 -> -14.014743 | D17: =D16/(1+Assumptions!C17)^2 -> 343.50725 | E17: =E16/(1+Assumptions!C17)^3 -> 293.4506 | F17: =F16/(1+Assumptions!C17)^4 -> 250.68331 | G17: =G16/(1+Assumptions!C17)^5 -> 214.14452 | H17: =H16/(1+Assumptions!C17)^6 -> 182.92769 | I17: =I16/(1+Assumptions!C17)^7 -> 156.25815 | J17: =J16/(1+Assumptions!C17)^8 -> 133.47392 | K17: =K16/(1+Assumptions!C17)^9 -> 114.00935 | L17: =L16/(1+Assumptions!C17)^10 -> 97.381093 | M17: =SUM(C17:L17) -> 1771.8211
B18: Cumulative NPV of Profit | C18: =C17 -> -14.014743 | D18: =C18+D17 -> 329.4925 | E18: =D18+E17 -> 622.9431 | F18: =E18+F17 -> 873.62642 | G18: =F18+G17 -> 1087.7709 | H18: =G18+H17 -> 1270.6986 | I18: =H18+I17 -> 1426.9568 | J18: =I18+J17 -> 1560.4307 | K18: =J18+K17 -> 1674.4401 | L18: =K18+L17 -> 1771.8211 | M18: =L18 -> 1771.8211
B20: Profit Criterion: The product is deemed acceptable if the Cumulative NPV of Profit (cell L17) > 0. A negative NPV means the product destroys shareholder value at the risk discount rate.

Sheet New Business
B1: NEW BUSINESS MODEL – Projected Cashflows from Future New Business
B3: Projects the aggregate cashflows arising from new policies expected to be sold over the next 5 years. Inputs: new business volumes and mix (model points). Each cohort is a new group of policies.
B5: New Business Volume Assumptions (number of new policies per year)
C6: Year 1 | D6: Year 2 | E6: Year 3 | F6: Year 4 | G6: Year 5 | H6: Total
C7: 300 | D7: 330 | E7: 360 | F7: 390 | G7: 420 | H7: =SUM(C7:G7) -> 1800 | I7: —
I8: =(E7-D7)/D7 -> 0.090909091
B9: Projected Aggregate Annual Premium Income (£)
B10: Cohort (policies sold in…) | C10: Yr 1 NB | D10: Yr 2 NB | E10: Yr 3 NB | F10: Yr 4 NB | G10: Yr 5 NB | H10: Total | I10: =(G7-F7)/F7 -> 0.076923077
B11: Policies from Year 1 cohort | C11: =C7*(1-Assumptions!C11)^0*(1-Assumptions!C12)^0*(1-Assumptions!C10)^0*Assumptions!C5 -> 180000 | D11: =C7*(1-Assumptions!C11)^1*(1-Assumptions!C12)^1*(1-Assumptions!C10)^1*Assumptions!C5 -> 166229.87 | E11: =C7*(1-Assumptions!C11)^2*(1-Assumptions!C12)^2*(1-Assumptions!C10)^2*Assumptions!C5 -> 153513.17 | F11: =C7*(1-Assumptions!C11)^3*(1-Assumptions!C12)^3*(1-Assumptions!C10)^3*Assumptions!C5 -> 141769.31 | G11: =C7*(1-Assumptions!C11)^4*(1-Assumptions!C12)^4*(1-Assumptions!C10)^4*Assumptions!C5 -> 130923.86 | H11: =SUM(C11:G11) -> 772436.21
B12: Policies from Year 2 cohort | C12: — | D12: =D7*(1-Assumptions!C11)^0*(1-Assumptions!C12)^0*(1-Assumptions!C10)^0*Assumptions!C5 -> 198000 | E12: =D7*(1-Assumptions!C11)^1*(1-Assumptions!C12)^1*(1-Assumptions!C10)^1*Assumptions!C5 -> 182852.86 | F12: =D7*(1-Assumptions!C11)^2*(1-Assumptions!C12)^2*(1-Assumptions!C10)^2*Assumptions!C5 -> 168864.49 | G12: =D7*(1-Assumptions!C11)^3*(1-Assumptions!C12)^3*(1-Assumptions!C10)^3*Assumptions!C5 -> 155946.24 | H12: =SUM(C12:G12) -> 705663.59
B13: Policies from Year 3 cohort | C13: — | D13: — | E13: =E7*(1-Assumptions!C11)^0*(1-Assumptions!C12)^0*(1-Assumptions!C10)^0*Assumptions!C5 -> 216000 | F13: =E7*(1-Assumptions!C11)^1*(1-Assumptions!C12)^1*(1-Assumptions!C10)^1*Assumptions!C5 -> 199475.85 | G13: =E7*(1-Assumptions!C11)^2*(1-Assumptions!C12)^2*(1-Assumptions!C10)^2*Assumptions!C5 -> 184215.81 | H13: =SUM(C13:G13) -> 599691.66
B14: Policies from Year 4 cohort | C14: — | D14: — | E14: — | F14: =F7*(1-Assumptions!C11)^0*(1-Assumptions!C12)^0*(1-Assumptions!C10)^0*Assumptions!C5 -> 234000 | G14: =F7*(1-Assumptions!C11)^1*(1-Assumptions!C12)^1*(1-Assumptions!C10)^1*Assumptions!C5 -> 216098.84 | H14: =SUM(C14:G14) -> 450098.84
B15: Policies from Year 5 cohort | C15: — | D15: — | E15: — | F15: — | G15: =G7*(1-Assumptions!C11)^0*(1-Assumptions!C12)^0*(1-Assumptions!C10)^0*Assumptions!C5 -> 252000 | H15: =SUM(C15:G15) -> 252000
B16: Total NB Premium Income (all cohorts) | C16: =SUM(C11:C15) -> 180000 | D16: =SUM(D11:D15) -> 364229.87 | E16: =SUM(E11:E15) -> 552366.03 | F16: =SUM(F11:F15) -> 744109.65 | G16: =SUM(G11:G15) -> 939184.74 | H16: =SUM(H11:H15) -> 2779890.3
B18: Projected Aggregate Claims (£)
B19: Total NB Claims Paid (all cohorts) | C19: =C16/Assumptions!C5*Assumptions!C10*Assumptions!C4*(1+Assumptions!C13)^(1-1) -> 7500 | D19: =D16/Assumptions!C5*Assumptions!C10*Assumptions!C4*(1+Assumptions!C13)^(2-1) -> 15479.77 | E19: =E16/Assumptions!C5*Assumptions!C10*Assumptions!C4*(1+Assumptions!C13)^(3-1) -> 23945.068 | F19: =F16/Assumptions!C5*Assumptions!C10*Assumptions!C4*(1+Assumptions!C13)^(4-1) -> 32902.296 | G19: =G16/Assumptions!C5*Assumptions!C10*Assumptions!C4*(1+Assumptions!C13)^(5-1) -> 42358.49 | H19: =SUM(C19:G19) -> 122185.62
B21: New Business Profit Contribution (simplified, £)
B22: Item | C22: Year 1 | D22: Year 2 | E22: Year 3 | F22: Year 4 | G22: Year 5 | H22: Total
B23: Premium Income | C23: =C16 -> 180000 | D23: =D16 -> 364229.87 | E23: =E16 -> 552366.03 | F23: =F16 -> 744109.65 | G23: =G16 -> 939184.74 | H23: =SUM(C23:G23) -> 2779890.3
B24: Less: Claims | C24: =-C19 -> -7500 | D24: =-D19 -> -15479.77 | E24: =-E19 -> -23945.068 | F24: =-F19 -> -32902.296 | G24: =-G19 -> -42358.49 | H24: =SUM(C24:G24) -> -122185.62
B25: Less: Expenses | C25: =-(C16/Assumptions!C5*(Assumptions!C18+Assumptions!C19)) -> -90000 | D25: =-(D16/Assumptions!C5*(Assumptions!C18+Assumptions!C19)) -> -182114.94 | E25: =-(E16/Assumptions!C5*(Assumptions!C18+Assumptions!C19)) -> -276183.02 | F25: =-(F16/Assumptions!C5*(Assumptions!C18+Assumptions!C19)) -> -372054.82 | G25: =-(G16/Assumptions!C5*(Assumptions!C18+Assumptions!C19)) -> -469592.37 | H25: =SUM(C25:G25) -> -1389945.1
B26: Less: Commission | C26: =-C16*Assumptions!C21 -> -9000 | D26: =-D16*Assumptions!C21 -> -18211.494 | E26: =-E16*Assumptions!C21 -> -27618.302 | F26: =-F16*Assumptions!C21 -> -37205.482 | G26: =-G16*Assumptions!C21 -> -46959.237 | H26: =SUM(C26:G26) -> -138994.51
B27: NB Pre-Tax Contribution | C27: =SUM(C23:C26) -> 73500 | D27: =SUM(D23:D26) -> 148423.67 | E27: =SUM(E23:E26) -> 224619.65 | F27: =SUM(F23:F26) -> 301947.04 | G27: =SUM(G23:G26) -> 380274.64 | H27: =SUM(C27:G27) -> 1128765

Sheet Existing Business
B1: EXISTING BUSINESS MODEL – Run-off of Current In-Force Portfolio
B3: Projects cashflows from policies already in-force today. The portfolio runs off over time as policies lapse, mature or result in claims. This is the 'existing business' component of the full model office.
B5: Current In-Force Portfolio (Model Points)
B6: Model Point / Segment | C6: Policies | D6: Avg Prem (£) | E6: Avg SA (£) | F6: Avg Remaining Term | G6: Annual Claims Est.
B7: MP1: Age 35, CI, 5yr rem | C7: 800 | D7: 480 | E7: 5000 | F7: 5 | G7: =C7*Assumptions!C10*E7 -> 20000
B8: MP2: Age 45, CI, 3yr rem | C8: 500 | D8: 600 | E8: 5000 | F8: 3 | G8: =C8*Assumptions!C10*E8 -> 12500
B9: MP3: Age 50, CI, 2yr rem | C9: 200 | D9: 720 | E9: 5000 | F9: 2 | G9: =C9*Assumptions!C10*E9 -> 5000
B10: Total In-Force | C10: =SUM(C7:C9) -> 1500 | G10: =SUM(G7:G9) -> 37500
B12: Run-Off Projection (total existing portfolio, £)
B13: Item | C13: Year 1 | D13: Year 2 | E13: Year 3 | F13: Year 4 | G13: Year 5 | H13: Total
B14: Policies In-Force (start yr) | C14: =C10 -> 1500 | D14: =C14*(1-Assumptions!C11)*(1-Assumptions!C12)*(1-Assumptions!C10) -> 1385.2489 | E14: =D14*(1-Assumptions!C11)*(1-Assumptions!C12)*(1-Assumptions!C10) -> 1279.2764 | F14: =E14*(1-Assumptions!C11)*(1-Assumptions!C12)*(1-Assumptions!C10) -> 1181.4109 | G14: =F14*(1-Assumptions!C11)*(1-Assumptions!C12)*(1-Assumptions!C10) -> 1091.0321
B15: (+) Premium Income | C15: =C14*(C7*D7+C8*D8+C9*D9)/C10 -> 828000 | D15: =D14*(C7*D7+C8*D8+C9*D9)/C10 -> 764657.42 | E15: =E14*(C7*D7+C8*D8+C9*D9)/C10 -> 706160.59 | F15: =F14*(C7*D7+C8*D8+C9*D9)/C10 -> 652138.81 | G15: =G14*(C7*D7+C8*D8+C9*D9)/C10 -> 602249.74 | H15: =SUM(C15:G15) -> 3553206.6
B16: (–) Claims | C16: =C14*Assumptions!C10*G10/C10/Assumptions!C10*(1+Assumptions!C13)^(1-1) -> 37500 | D16: =D14*Assumptions!C10*G10/C10/Assumptions!C10*(1+Assumptions!C13)^(2-1) -> 35323.848 | E16: =E14*Assumptions!C10*G10/C10/Assumptions!C10*(1+Assumptions!C13)^(3-1) -> 33273.98 | F16: =F14*Assumptions!C10*G10/C10/Assumptions!C10*(1+Assumptions!C13)^(4-1) -> 31343.067 | G16: =G14*Assumptions!C10*G10/C10/Assumptions!C10*(1+Assumptions!C13)^(5-1) -> 29524.207 | H16: =SUM(C16:G16) -> 166965.1
B17: (–) Expenses | C17: =C14*Assumptions!C19 -> 75000 | D17: =D14*Assumptions!C19 -> 69262.447 | E17: =E14*Assumptions!C19 -> 63963.822 | F17: =F14*Assumptions!C19 -> 59070.545 | G17: =G14*Assumptions!C19 -> 54551.607 | H17: =SUM(C17:G17) -> 321848.42
B18: Existing Business Profit | C18: =C15-C16-C17 -> 715500 | D18: =D15-D16-D17 -> 660071.12 | E18: =E15-E16-E17 -> 608922.79 | F18: =F15-F16-F17 -> 561725.2 | G18: =G15-G16-G17 -> 518173.92 | H18: =SUM(C18:G18) -> 3064393

Sheet Model Office
B1: FULL MODEL OFFICE – Combined New Business + Existing Business Projection
B3: The Full Model Office sums the new business and existing business projections. This is the key tool for management reporting, solvency assessment, embedded value, and strategic decision-making (SP1 Ch11). Green cells link from other sheets.
B5: Item | C5: Year 1 | D5: Year 2 | E5: Year 3 | F5: Year 4 | G5: Year 5 | H5: 5-Yr Total | I5: NPV @ RDR
B6: INCOME
B7: (+) New Business Premium | C7: ='New Business'!C16 -> 180000 | D7: ='New Business'!D16 -> 364229.87 | E7: ='New Business'!E16 -> 552366.03 | F7: ='New Business'!F16 -> 744109.65 | G7: ='New Business'!G16 -> 939184.74 | H7: =SUM(C7:G7) -> 2779890.3 | I7: =C7/(1+Assumptions!C17)^1+D7/(1+Assumptions!C17)^2+E7/(1+Assumptions!C17)^3+F7/(1+Assumptions!C17)^4+G7/(1+Assumptions!C17)^5 -> 2103557.2
B8: (+) Existing Business Premium | C8: ='Existing Business'!C15 -> 828000 | D8: ='Existing Business'!D15 -> 764657.42 | E8: ='Existing Business'!E15 -> 706160.59 | F8: ='Existing Business'!F15 -> 652138.81 | G8: ='Existing Business'!G15 -> 602249.74 | H8: =SUM(C8:G8) -> 3553206.6 | I8: =C8/(1+Assumptions!C17)^1+D8/(1+Assumptions!C17)^2+E8/(1+Assumptions!C17)^3+F8/(1+Assumptions!C17)^4+G8/(1+Assumptions!C17)^5 -> 2872032.8
B9: Total Premium Income | C9: =C7+C8 -> 1008000 | D9: =D7+D8 -> 1128887.3 | E9: =E7+E8 -> 1258526.6 | F9: =F7+F8 -> 1396248.5 | G9: =G7+G8 -> 1541434.5 | H9: =SUM(C9:G9) -> 6333096.9 | I9: =C9/(1+Assumptions!C17)^1+D9/(1+Assumptions!C17)^2+E9/(1+Assumptions!C17)^3+F9/(1+Assumptions!C17)^4+G9/(1+Assumptions!C17)^5 -> 4975589.9
B10: OUTGO
B11: (–) New Business Claims | C11: ='New Business'!C19 -> 7500 | D11: ='New Business'!D19 -> 15479.77 | E11: ='New Business'!E19 -> 23945.068 | F11: ='New Business'!F19 -> 32902.296 | G11: ='New Business'!G19 -> 42358.49 | H11: =SUM(C11:G11) -> 122185.62 | I11: =C11/(1+Assumptions!C17)^1+D11/(1+Assumptions!C17)^2+E11/(1+Assumptions!C17)^3+F11/(1+Assumptions!C17)^4+G11/(1+Assumptions!C17)^5 -> 92236.865
B12: (–) Existing Business Claims | C12: ='Existing Business'!C16 -> 37500 | D12: ='Existing Business'!D16 -> 35323.848 | E12: ='Existing Business'!E16 -> 33273.98 | F12: ='Existing Business'!F16 -> 31343.067 | G12: ='Existing Business'!G16 -> 29524.207 | H12: =SUM(C12:G12) -> 166965.1 | I12: =C12/(1+Assumptions!C17)^1+D12/(1+Assumptions!C17)^2+E12/(1+Assumptions!C17)^3+F12/(1+Assumptions!C17)^4+G12/(1+Assumptions!C17)^5 -> 134552.46
B13: Total Claims | C13: =C11+C12 -> 45000 | D13: =D11+D12 -> 50803.618 | E13: =E11+E12 -> 57219.048 | F13: =F11+F12 -> 64245.363 | G13: =G11+G12 -> 71882.697 | H13: =SUM(C13:G13) -> 289150.73 | I13: =C13/(1+Assumptions!C17)^1+D13/(1+Assumptions!C17)^2+E13/(1+Assumptions!C17)^3+F13/(1+Assumptions!C17)^4+G13/(1+Assumptions!C17)^5 -> 226789.32
B15: PROFIT SUMMARY
B16: Profit Component | C16: Year 1 | D16: Year 2 | E16: Year 3 | F16: Year 4 | G16: Year 5 | H16: 5-Yr Total | I16: NPV @ RDR
B17: New Business Profit Contribution | C17: ='New Business'!C27 -> 73500 | D17: ='New Business'!D27 -> 148423.67 | E17: ='New Business'!E27 -> 224619.65 | F17: ='New Business'!F27 -> 301947.04 | G17: ='New Business'!G27 -> 380274.64 | H17: =SUM(C17:G17) -> 1128765 | I17: =C17/(1+Assumptions!C17)^1+D17/(1+Assumptions!C17)^2+E17/(1+Assumptions!C17)^3+F17/(1+Assumptions!C17)^4+G17/(1+Assumptions!C17)^5 -> 854363.87
B18: Existing Business Profit Contribution | C18: ='Existing Business'!C18 -> 715500 | D18: ='Existing Business'!D18 -> 660071.12 | E18: ='Existing Business'!E18 -> 608922.79 | F18: ='Existing Business'!F18 -> 561725.2 | G18: ='Existing Business'!G18 -> 518173.92 | H18: =SUM(C18:G18) -> 3064393 | I18: =C18/(1+Assumptions!C17)^1+D18/(1+Assumptions!C17)^2+E18/(1+Assumptions!C17)^3+F18/(1+Assumptions!C17)^4+G18/(1+Assumptions!C17)^5 -> 2477332.4
B19: TOTAL MODEL OFFICE PROFIT (Pre-Tax) | C19: =C17+C18 -> 789000 | D19: =D17+D18 -> 808494.8 | E19: =E17+E18 -> 833542.44 | F19: =F17+F18 -> 863672.25 | G19: =G17+G18 -> 898448.57 | H19: =SUM(C19:G19) -> 4193158 | I19: =C19/(1+Assumptions!C17)^1+D19/(1+Assumptions!C17)^2+E19/(1+Assumptions!C17)^3+F19/(1+Assumptions!C17)^4+G19/(1+Assumptions!C17)^5 -> 3331696.3
B20: Discounted Profit (NPV @ Risk Discount Rate) | C20: =C19/(1+Assumptions!C17)^1 -> 730555.56 | D20: =D19/(1+Assumptions!C17)^2 -> 693153.98 | E20: =E19/(1+Assumptions!C17)^3 -> 661692.86 | F20: =F19/(1+Assumptions!C17)^4 -> 634824.88 | G20: =G19/(1+Assumptions!C17)^5 -> 611469 | H20: =SUM(C20:G20) -> 3331696.3 | I20: =C20/(1+Assumptions!C17)^1+D20/(1+Assumptions!C17)^2+E20/(1+Assumptions!C17)^3+F20/(1+Assumptions!C17)^4+G20/(1+Assumptions!C17)^5 -> 2678752
B22: KEY METRICS SUMMARY
B23: 5-Year Cumulative NPV of Profit (£) | C23: =I20 -> 2678752
B24: Total Policies In-Force – Year 5 (New+Existing) | C24: ='Existing Business'!G14+'New Business'!G7 -> 1511.0321
B25: Average Annual Premium Income (£) | C25: =H9/5 -> 1266619.4
B26: Claims Ratio (5-yr avg) | C26: =H13/H9 -> 0.045657083
B28: SENSITIVITY ANALYSIS GUIDE
B29: Test 1: Claims +10% | C29: Change 'Assumptions'!C10 from 0.5% to 0.55%. Observe impact on Row 19.
B30: Test 2: Lapse rate +5% | C30: Change 'Assumptions'!C12 from 7% to 12%. NB volumes reduce.
B31: Test 3: Investment return −1% | C31: Change 'Assumptions'!C16 from 4% to 3%. Reduces inv. income in profit test.
B32: Test 4: New biz volume −20% | C32: Change 'New Business'!C7:G7 downward. Tests NB sensitivity.
