Workbook

Sheet Dashboard
A1: SOLVENCY II INTERNAL MODEL – HEALTH & CARE INSURANCE | Prototype
A2: Reporting Date: 31 December 2024 | Currency: EUR (000s) | Model Version: 1.0
A4: SCR Coverage Ratio | C4: Own Funds (€000s) | E4: SCR Total (€000s) | G4: MCR (€000s) | I4: MCR Coverage | K4: Combined Ratio
A5: ='SCR Summary'!C50 -> 0.19097649 | C5: ='Own Funds'!C35 -> 26000 | E5: ='SCR Summary'!C38 -> 136142.41 | G5: ='SCR Summary'!C44 -> 34035.603 | I5: ='SCR Summary'!C51 -> 0.68751537 | K5: =Underwriting!F33 -> 0.82964292
A8: MODEL NAVIGATION
A10: → Assumptions | B10: Key input assumptions for all risk modules
A11: → Underwriting | B11: Premium, claims, expense analysis & combined ratio
A12: → Own Funds | B12: Balance sheet, Solvency II own funds by tier
A13: → Health UW Risk | B13: Health underwriting risk – SLT & Non-SLT sub-modules
A14: → Market Risk | B14: Market risk SCR – interest rate, equity, spread, FX, concentration
A15: → Credit Risk | B15: Counterparty default risk (Type 1 & Type 2)
A16: → Op Risk | B16: Operational risk capital charge
A17: → SCR Summary | B17: Aggregated SCR using correlation matrices
A18: → ORSA Summary | B18: Own Risk & Solvency Assessment narrative dashboard

Sheet Assumptions
A1: KEY MODEL ASSUMPTIONS
A3: A. HEALTH UNDERWRITING ASSUMPTIONS
A4: Parameter | B4: Value | C4: Unit | D4: Min | E4: Max | F4: Source / Notes
A5: Gross Written Premium (€000s) | B5: 500000 | C5: €000s | D5: 400000 | E5: 600000 | F5: Business plan
A6: Claims Ratio – Medical Expense | B6: 0.68 | C6: % | D6: 0.6 | E6: 0.78 | F6: 5yr avg internal data
A7: Claims Ratio – Income Protection | B7: 0.72 | C7: % | D7: 0.65 | E7: 0.82 | F7: 5yr avg internal data
A8: Claims Ratio – Long-Term Care | B8: 0.75 | C8: % | D8: 0.68 | E8: 0.85 | F8: Actuarial best estimate
A9: Expense Ratio | B9: 0.18 | C9: % | D9: 0.15 | E9: 0.22 | F9: Finance dept
A10: Lapse Rate – Medical Expense | B10: 0.05 | C10: % | D10: 0.03 | E10: 0.08 | F10: Experience study 2023
A11: Lapse Rate – Income Protection | B11: 0.03 | C11: % | D11: 0.02 | E11: 0.05 | F11: Experience study 2023
A12: Premium Growth Rate | B12: 0.04 | C12: % | D12: 0 | E12: 0.08 | F12: Business plan
A13: Reinsurance Premium Ceded (%) | B13: 0.08 | C13: % | D13: 0.05 | E13: 0.12 | F13: RI treaty
A14: Reinsurance Claims Recovered (%) | B14: 0.1 | C14: % | D14: 0.06 | E14: 0.15 | F14: RI treaty
A17: B. MARKET RISK ASSUMPTIONS
A18: Parameter | B18: Value | C18: Unit | D18: Min | E18: Max | F18: Source / Notes
A19: Investment Portfolio – Total (€000s) | B19: 800000 | C19: €000s | F19: Investment dept
A20: Government Bonds (%) | B20: 0.45 | C20: % | F20: Investment dept
A21: Corporate Bonds (%) | B21: 0.3 | C21: % | F21: Investment dept
A22: Equities (%) | B22: 0.1 | C22: % | F22: Investment dept
A23: Property (%) | B23: 0.08 | C23: % | F23: Investment dept
A24: Cash & Other (%) | B24: 0.07 | C24: % | F24: Investment dept
A25: Duration of Bond Portfolio (years) | B25: 6.5 | C25: years | D25: 4 | E25: 9 | F25: Investment dept
A26: Average Credit Quality (Moody's equiv) | B26: A2 | C26: – | F26: Rating agency
A27: Interest Rate Up Shock (%) | B27: 0.013 | C27: bps | F27: EIOPA standard
A28: Interest Rate Down Shock (%) | B28: -0.009 | C28: bps | F28: EIOPA standard
A29: Equity Stress Type 1 (%) | B29: 0.39 | C29: % | F29: EIOPA Art.169
A30: Equity Stress Type 2 (%) | B30: 0.49 | C30: % | F30: EIOPA Art.169
A31: Property Stress (%) | B31: 0.25 | C31: % | F31: EIOPA Art.174
A34: C. OPERATIONAL RISK ASSUMPTIONS
A35: Parameter | B35: Value | C35: Unit | D35: Min | E35: Max | F35: Source / Notes
A36: Op Risk Factor – Technical Provisions | B36: 0.0045 | C36: % | D36: 0.003 | E36: 0.006 | F36: EIOPA Delegated Reg.
A37: Op Risk Factor – Premiums | B37: 0.03 | C37: % | D37: 0.025 | E37: 0.04 | F37: EIOPA Delegated Reg.
A38: Expense Op Risk Cap (%) | B38: 0.3 | C38: % | F38: Internal policy

Sheet Underwriting
A1: UNDERWRITING ACCOUNT – HEALTH & CARE INSURANCE
A3: PREMIUM INCOME (€000s)
A4: Item | B4: Medical Expense | C4: Income Protection | D4: Long-Term Care | E4: Group Health | F4: Total | G4: Notes
A5: Gross Written Premium | B5: 220000 | C5: 130000 | D5: 90000 | E5: 60000 | F5: =SUM(B5:E5) -> 500000 | G5: Source: Business Plan 2024
A6: Reinsurance Premium Ceded | B6: =-B5*Assumptions!$B$13 -> -17600 | C6: =-C5*Assumptions!$B$13 -> -10400 | D6: =-D5*Assumptions!$B$13 -> -7200 | E6: =-E5*Assumptions!$B$13 -> -4800 | F6: =SUM(B6:E6) -> -40000
A7: Net Written Premium | B7: =B5+B6 -> 202400 | C7: =C5+C6 -> 119600 | D7: =D5+D6 -> 82800 | E7: =E5+E6 -> 55200 | F7: =SUM(B7:E7) -> 460000
A8: Change in Unearned Premium Reserve | B8: 2000 | C8: -1500 | D8: 500 | E8: 800 | F8: =SUM(B8:E8) -> 1800
A9: Net Earned Premium | B9: =B7+B8 -> 204400 | C9: =C7+C8 -> 118100 | D9: =D7+D8 -> 83300 | E9: =E7+E8 -> 56000 | F9: =SUM(B9:E9) -> 461800
A11: CLAIMS INCURRED (€000s)
A12: Item | B12: Medical Expense | C12: Income Protection | D12: Long-Term Care | E12: Group Health | F12: Total | G12: Notes
A13: Gross Claims Incurred | B13: =-B9*0.68 -> -138992 | C13: =-C9*0.72 -> -85032 | D13: =-D9*0.75 -> -62475 | E13: =-E9*0.7 -> -39200 | F13: =SUM(B13:E13) -> -325699
A14: Reinsurance Claims Recovered | B14: =-B13*Assumptions!$B$14 -> 13899.2 | C14: =-C13*Assumptions!$B$14 -> 8503.2 | D14: =-D13*Assumptions!$B$14 -> 6247.5 | E14: =-E13*Assumptions!$B$14 -> 3920 | F14: =SUM(B14:E14) -> 32569.9
A15: Net Claims Incurred | B15: =B13+B14 -> -125092.8 | C15: =C13+C14 -> -76528.8 | D15: =D13+D14 -> -56227.5 | E15: =E13+E14 -> -35280 | F15: =SUM(B15:E15) -> -293129.1
A17: EXPENSES (€000s)
A18: Item | B18: Medical Expense | C18: Income Protection | D18: Long-Term Care | E18: Group Health | F18: Total | G18: Notes
A19: Acquisition Expenses | B19: =-B5*0.1 -> -22000 | C19: =-C5*0.1 -> -13000 | D19: =-D5*0.1 -> -9000 | E19: =-E5*0.1 -> -6000 | F19: =SUM(B19:E19) -> -50000
A20: Administration Expenses | B20: =-B5*0.08 -> -17600 | C20: =-C5*0.08 -> -10400 | D20: =-D5*0.08 -> -7200 | E20: =-E5*0.08 -> -4800 | F20: =SUM(B20:E20) -> -40000
A21: Total Expenses | B21: =B19+B20 -> -39600 | C21: =C19+C20 -> -23400 | D21: =D19+D20 -> -16200 | E21: =E19+E20 -> -10800 | F21: =SUM(B21:E21) -> -90000
A23: TECHNICAL RESULT (€000s)
A24: Item | B24: Medical Expense | C24: Income Protection | D24: Long-Term Care | E24: Group Health | F24: Total | G24: Notes
A25: Technical Result (Net) | B25: =B9+B15+B21 -> 39707.2 | C25: =C9+C15+C21 -> 18171.2 | D25: =D9+D15+D21 -> 10872.5 | E25: =E9+E15+E21 -> 9920 | F25: =SUM(B25:E25) -> 78670.9
A27: KEY RATIOS
A28: Ratio | B28: Medical Expense | C28: Income Protection | D28: Long-Term Care | E28: Group Health | F28: Total | G28: Total
A29: Gross Claims Ratio | B29: =IF(B9=0,0,-B13/B9) -> 0.68 | C29: =IF(C9=0,0,-C13/C9) -> 0.72 | D29: =IF(D9=0,0,-D13/D9) -> 0.75 | E29: =IF(E9=0,0,-E13/E9) -> 0.7 | F29: =IF(F9=0,0,-F13/F9) -> 0.70528151
A30: Net Claims Ratio | B30: =IF(B9=0,0,-B15/B9) -> 0.612 | C30: =IF(C9=0,0,-C15/C9) -> 0.648 | D30: =IF(D9=0,0,-D15/D9) -> 0.675 | E30: =IF(E9=0,0,-E15/E9) -> 0.63 | F30: =IF(F9=0,0,-F15/F9) -> 0.63475336
A31: Expense Ratio | B31: =IF(B9=0,0,-B21/B9) -> 0.19373777 | C31: =IF(C9=0,0,-C21/C9) -> 0.19813717 | D31: =IF(D9=0,0,-D21/D9) -> 0.19447779 | E31: =IF(E9=0,0,-E21/E9) -> 0.19285714 | F31: =IF(F9=0,0,-F21/F9) -> 0.19488956
A32: Reinsurance Ratio | B32: =IF(B5=0,0,-B6/B5) -> 0.08 | C32: =IF(C5=0,0,-C6/C5) -> 0.08 | D32: =IF(D5=0,0,-D6/D5) -> 0.08 | E32: =IF(E5=0,0,-E6/E5) -> 0.08 | F32: =IF(F5=0,0,-F6/F5) -> 0.08
A33: Combined Ratio | B33: =B30+B31 -> 0.80573777 | C33: =C30+C31 -> 0.84613717 | D33: =D30+D31 -> 0.86947779 | E33: =E30+E31 -> 0.82285714 | F33: =F30+F31 -> 0.82964292
A35: Combined Ratio (Total) | I35: =F33 -> 0.82964292

Sheet Own Funds
A1: OWN FUNDS – SOLVENCY II BALANCE SHEET (€000s)
A3: Item | B3: IFRS BV (€000s) | C3: SII Adj (€000s) | D3: SII Value (€000s) | E3: Notes
A4: ASSETS
A5: Investments – Government Bonds | B5: 360000 | C5: 5000 | D5: =B5+C5 -> 365000
A6: Investments – Corporate Bonds | B6: 240000 | C6: -8000 | D6: =B6+C6 -> 232000
A7: Investments – Equities | B7: 80000 | C7: 12000 | D7: =B7+C7 -> 92000
A8: Investments – Property | B8: 64000 | C8: 6000 | D8: =B8+C8 -> 70000
A9: Investments – Cash & Other | B9: 56000 | C9: 0 | D9: =B9+C9 -> 56000
A10: Reinsurance Recoverables | B10: 45000 | C10: -3000 | D10: =B10+C10 -> 42000
A11: Deferred Tax Asset | B11: 8000 | C11: -8000 | D11: =B11+C11 -> 0
A12: Receivables & Other Assets | B12: 22000 | C12: -5000 | D12: =B12+C12 -> 17000
A13: TOTAL ASSETS | B13: =SUM(B5:B12) -> 875000 | C13: =SUM(C5:C12) -> -1000 | D13: =SUM(D5:D12) -> 874000
A15: LIABILITIES
A16: Best Estimate Liabilities – Medical Expense | B16: 155000 | C16: -12000 | D16: =B16+C16 -> 143000
A17: Best Estimate Liabilities – Income Protection | B17: 98000 | C17: -8000 | D17: =B17+C17 -> 90000
A18: Best Estimate Liabilities – Long-Term Care | B18: 145000 | C18: -10000 | D18: =B18+C18 -> 135000
A19: Risk Margin | B19: 0 | C19: 18000 | D19: =B19+C19 -> 18000
A20: Technical Provisions – Total | B20: =B16+B17+B18 -> 398000 | C20: =C16+C17+C18+C19 -> -12000 | D20: =D16+D17+D18+D19 -> 386000
A21: Financial Liabilities | B21: 35000 | C21: -1000 | D21: =B21+C21 -> 34000
A22: Payables & Other Liabilities | B22: 28000 | C22: -2000 | D22: =B22+C22 -> 26000
A23: Deferred Tax Liability | B23: 12000 | C23: 4000 | D23: =B23+C23 -> 16000
A24: TOTAL LIABILITIES | B24: =SUM(B16:B23) -> 871000 | C24: =SUM(C16:C23) -> -23000 | D24: =SUM(D16:D23) -> 848000
A26: EXCESS OF ASSETS OVER LIABILITIES (OWN FUNDS)
A27: Excess of Assets over Liabilities | D27: =D13-D24 -> 26000
A29: OWN FUNDS BY TIER
A30: Tier | B30: Description | C30: Amount (€000s) | D30: % of Total | E30: Eligible for SCR
A31: Tier 1 Unrestricted | B31: Ordinary share capital + reserves | C31: =D27*0.82 -> 21320 | D31: =C31/C35 -> 0.82 | E31: 100%
A32: Tier 1 Restricted | B32: Subordinated liabilities (perpetual) | C32: =D27*0.08 -> 2080 | D32: =C32/C35 -> 0.08 | E32: 20% cap
A33: Tier 2 | B33: Subordinated liabilities (dated) | C33: =D27*0.07 -> 1820 | D33: =C33/C35 -> 0.07 | E33: 50% cap
A34: Tier 3 | B34: Deferred tax & other | C34: =D27*0.03 -> 780 | D34: =C34/C35 -> 0.03 | E34: 15% cap
A35: TOTAL OWN FUNDS (€000s) | C35: =SUM(C31:C34) -> 26000

Sheet Health UW Risk
A1: HEALTH UNDERWRITING RISK SCR (€000s)
A3: A. SLT (SIMILAR TO LIFE TECHNIQUES) – INCOME PROTECTION & LTC
A4: Sub-Module | B4: Stress | C4: Best Estimate (€000s) | D4: SCR (€000s) | E4: Notes | F4: Reference
A5: Mortality Risk | B5: 15% increase in mortality rates | C5: 22000 | D5: =C5*0.15 -> 3300 | E5: TP shock | F5: Art. 137 SII DR
A6: Longevity Risk | B6: 20% decrease in mortality rates | C6: 45000 | D6: =C6*0.2 -> 9000 | E6: TP shock | F6: Art. 138 SII DR
A7: Disability-Morbidity | B7: 35% increase in incidence Year 1 | C7: 68000 | D7: =C7*0.35 -> 23800 | E7: IP & LTC | F7: Art. 139 SII DR
A8: Lapse Risk | B8: 50% permanent lapse shock | C8: 35000 | D8: =C8*0.5 -> 17500 | E8: IP book | F8: Art. 142 SII DR
A9: Expense Risk SLT | B9: 10% expense + 1% inflation pa | C9: 12000 | D9: =C9*0.1 -> 1200 | E9: Admin exp | F9: Art. 141 SII DR
A10: Revision Risk | B10: 3% increase in annuity amounts | C10: 8000 | D10: =C10*0.03 -> 240 | E10: Annuities | F10: Art. 143 SII DR
A13: SLT Correlation Matrix (EIOPA prescribed)
B14: Mort | C14: Long | D14: Dis | E14: Lapse | F14: Exp | G14: Rev
A15: Mort | B15: 1 | C15: 0 | D15: 0.5 | E15: 0 | F15: 0.25 | G15: 0
A16: Long | B16: 0 | C16: 1 | D16: 0 | E16: 0.25 | F16: 0.25 | G16: 0.25
A17: Dis | B17: 0.5 | C17: 0 | D17: 1 | E17: 0 | F17: 0.5 | G17: 0
A18: Lapse | B18: 0 | C18: 0.25 | D18: 0 | E18: 1 | F18: 0.5 | G18: 0
A19: Exp | B19: 0.25 | C19: 0.25 | D19: 0.5 | E19: 0.5 | F19: 1 | G19: 0
A20: Rev | B20: 0 | C20: 0.25 | D20: 0 | E20: 0 | F20: 0 | G20: 1
A22: SLT Health UW SCR (aggregated) | D22: =SQRT(D5^2+D6^2+D7^2+D8^2+D9^2+D10^2+2*0.5*D5*D7+2*0.25*D5*D9+2*0.25*D6*D8+2*0.25*D6*D9+2*0.25*D6*D10+2*0.5*D7*D9+2*0.5*D8*D9) -> 34371.319
A24: B. NON-SLT (SIMILAR TO NON-LIFE TECHNIQUES) – MEDICAL EXPENSE & GROUP
A25: Sub-Module | B25: Stress | C25: Exposure (€000s) | D25: SCR (€000s) | E25: Notes | F25: Reference
A26: Premium & Reserve Risk | B26: Combined NP formula | C26: 420000 | D26: =C26*0.085 -> 35700 | E26: Med Exp | F26: Art. 148 SII DR
A27: Lapse Risk Non-SLT | B27: 40% lapse shock | C27: 85000 | D27: =C27*0.4 -> 34000 | E27: Group | F27: Art. 159 SII DR
A28: CAT Risk – Pandemic | B28: 1-in-200 pandemic scenario | C28: 50000 | D28: =C28*0.5 -> 25000 | E28: All LoB | F28: Art. 160 SII DR
A29: CAT Risk – Mass Accident | B29: Accident concentration | C29: 15000 | D29: =C29*0.2 -> 3000 | E29: Group | F29: Art. 160 SII DR
A31: Non-SLT Health UW SCR (aggregated) | D31: =SQRT(D26^2+D27^2+D28^2+D29^2+2*0.5*D26*D28) -> 62904.61
A33: TOTAL HEALTH UW RISK SCR (€000s) | D33: =SQRT(D22^2+D31^2+2*0.5*D22*D31) -> 85442.917

Sheet Market Risk
A1: MARKET RISK SCR (€000s)
A3: MARKET RISK SUB-MODULES
A4: Sub-Module | B4: Stress | C4: Exposure (€000s) | D4: SCR (€000s) | E4: Notes | F4: Reference
A5: Interest Rate Risk (Up) | B5: +130bps parallel shift | C5: =800000*0.45+800000*0.3 -> 600000 | D5: =C5*6.5*0.013 -> 50700 | E5: Bond port | F5: Art.165 SII DR
A6: Interest Rate Risk (Down) | B6: -90bps parallel shift | C6: =800000*0.45+800000*0.3 -> 600000 | D6: =C6*6.5*0.009 -> 35100 | E6: Bond port | F6: Art.165 SII DR
A7: Equity Risk – Type 1 | B7: 39% stress | C7: =800000*0.1 -> 80000 | D7: =C7*0.39 -> 31200 | E7: Listed eq | F7: Art.169 SII DR
A8: Equity Risk – Type 2 | B8: 49% stress | C8: =800000*0.05 -> 40000 | D8: =C8*0.49 -> 19600 | E8: PE/infra | F8: Art.169 SII DR
A9: Property Risk | B9: 25% stress | C9: =800000*0.08 -> 64000 | D9: =C9*0.25 -> 16000 | E9: Property | F9: Art.174 SII DR
A10: Spread Risk – Bonds | B10: Duration-based stress | C10: =800000*0.3 -> 240000 | D10: =C10*6.5*0.003 -> 4680 | E10: Corp bds | F10: Art.176 SII DR
A11: Currency Risk | B11: 25% stress | C11: =800000*0.05 -> 40000 | D11: =C11*0.25 -> 10000 | E11: FX exposure | F11: Art.178 SII DR
A12: Concentration Risk | B12: Asset concentration adj. | C12: =800000*0.1 -> 80000 | D12: =C12*0.12 -> 9600 | E12: Top 5 issuers | F12: Art.182 SII DR
A13: Illiquidity Premium Risk | B13: 65% illiq prem reduction | C13: =100000 -> 100000 | D13: =C13*0.05 -> 5000 | E13: Ann liabs | F13: Art.167 SII DR
A15: Interest Rate SCR (max up/down) | D15: =MAX(D5,D6) -> 50700
A17: Market Risk Correlation Matrix (EIOPA Art.164)
B18: Int Rate | C18: Equity | D18: Property | E18: Spread | F18: Currency | G18: Conc
A19: Int Rate | B19: 1 | C19: 0 | D19: 0 | E19: 0.25 | F19: 0.25 | G19: 0
A20: Equity | B20: 0 | C20: 1 | D20: 0.75 | E20: 0.75 | F20: 0.25 | G20: 0
A21: Property | B21: 0 | C21: 0.75 | D21: 1 | E21: 0.5 | F21: 0.25 | G21: 0
A22: Spread | B22: 0.25 | C22: 0.75 | D22: 0.5 | E22: 1 | F22: 0.25 | G22: 0
A23: Currency | B23: 0.25 | C23: 0.25 | D23: 0.25 | E23: 0.25 | F23: 1 | G23: 0
A24: Conc | B24: 0 | C24: 0 | D24: 0 | E24: 0 | F24: 0 | G24: 1
A26: TOTAL MARKET RISK SCR (€000s) | D26: =SQRT(D15^2+D7^2+D8^2+D9^2+D10^2+D11^2+D12^2+2*0.75*D7*D9+2*0.75*D7*D10+2*0.5*D9*D10+2*0.25*D15*D10+2*0.25*D15*D11) -> 76242.996

Sheet Credit Risk
A1: COUNTERPARTY DEFAULT RISK SCR (€000s)
A3: TYPE 1 EXPOSURES – Reinsurance, Derivatives, Deposits
A4: Counterparty | B4: Rating | C4: Exposure (€000s) | D4: LGD (€000s) | E4: PD (%) | F4: SCR (€000s)
A5: Munich Re | B5: AA | C5: 35000 | D5: =C5*0.5 -> 17500 | E5: 0.001 | F5: =D5*E5^0.5*3 -> 1660.1958
A6: Swiss Re | B6: AA | C6: 28000 | D6: =C6*0.5 -> 14000 | E6: 0.001 | F6: =D6*E6^0.5*3 -> 1328.1566
A7: Hannover Re | B7: A+ | C7: 18000 | D7: =C7*0.5 -> 9000 | E7: 0.002 | F7: =D7*E7^0.5*3 -> 1207.4767
A8: SCOR SE | B8: A | C8: 12000 | D8: =C8*0.5 -> 6000 | E8: 0.005 | F8: =D8*E8^0.5*3 -> 1272.7922
A9: Barclays Bank | B9: A | C9: 8000 | D9: =C9*0.5 -> 4000 | E9: 0.005 | F9: =D9*E9^0.5*3 -> 848.52814
A10: Type 1 SCR (before diversification) | F10: =SQRT(SUM(F5:F9)^2*1) -> 6317.1494
A12: TYPE 2 EXPOSURES – Receivables, Intermediaries
A13: Category | B13: Overdue (days) | C13: Amount (€000s) | D13: Stress Factor | E13: SCR (€000s) | F13: Notes
A14: Premium receivables <3m | B14: <90 | C14: 18000 | D14: 0 | E14: =C14*D14 -> 0 | F14: Standard
A15: Premium receivables 3-6m | B15: 90-180 | C15: 5000 | D15: 0.9 | E15: =C15*D15 -> 4500 | F15: Near default
A16: Intermediary receivables | B16: Misc | C16: 3500 | D16: 0.15 | E16: =C16*D16 -> 525 | F16: Standard
A17: Other receivables | B17: Misc | C17: 2000 | D17: 0.15 | E17: =C17*D17 -> 300 | F17: Standard
A18: Type 2 SCR | E18: =SUM(E14:E17) -> 5325
A20: TOTAL COUNTERPARTY DEFAULT RISK SCR (€000s) | F20: =SQRT(F10^2+E18^2+2*0.5*F10*E18) -> 10094.594

Sheet Op Risk
A1: OPERATIONAL RISK SCR (€000s)
A3: OPERATIONAL RISK CAPITAL CHARGE (EIOPA Art.204)
A4: Component | B4: Input / Formula | C4: Value (€000s) | D4: Reference
A5: Gross Technical Provisions (Life-like) | B5: 243000 | C5: 243000
A6: Gross Technical Provisions (Non-life) | B6: 125000 | C6: 125000
A7: Gross Written Premiums – prior year | B7: 480000 | C7: 480000 | D7: Business Plan
A8: Gross Written Premiums – current year | B8: =Underwriting!F5 -> 500000 | C8: =Underwriting!F5 -> 500000 | D8: Business Plan
A9: Op Risk on TPs (Life) | B9: TP * 0.45% | C9: =C5*0.0045 -> 1093.5 | D9: Art.204(1)(a)
A10: Op Risk on TPs (Non-Life) | B10: TP * 0.45% | C10: =C6*0.0045 -> 562.5 | D10: Art.204(1)(a)
A11: Op Risk on Premiums | B11: max(GWP_t,GWP_{t-1}) * 3% | C11: =MAX(C7,C8)*0.03 -> 15000 | D11: Art.204(1)(b)
A12: Basic Op Risk (before cap) | B12: sum of above | C12: =C9+C10+C11 -> 16656 | D12: Art.204(4)
A13: 30% of BSCR (cap check) | B13: 30% * BSCR | C13: =C12*1.3 -> 21652.8 | D13: Art.204(4)
A14: OPERATIONAL RISK SCR | B14: min(Basic, Cap) | C14: =MIN(C12,C13) -> 16656 | D14: Art.204
A17: OPERATIONAL RISK HEAT MAP (Qualitative)
A18: Risk Category | B18: Residual Risk Level | C18: Key Controls
A19: Fraud & Unauthorised Activities | B19: High | C19: Segregation of duties, IT access controls
A20: Business Disruption & System Failure | B20: Medium | C20: BCP/DR programme
A21: Compliance & Legal Risk | B21: Medium | C21: Legal review, compliance monitoring
A22: Outsourcing Risk | B22: Low | C22: Vendor management policy
A23: People & HR Risk | B23: Low | C23: HR policies, key-man insurance
A24: Claims Fraud | B24: High | C24: Anti-fraud analytics, SIU
A25: Data Privacy / GDPR | B25: Medium | C25: Data governance framework
A26: Cyber Risk | B26: High | C26: Cyber insurance, pen testing

Sheet SCR Summary
A1: SOLVENCY CAPITAL REQUIREMENT – SUMMARY (€000s)
A3: Risk Module | B3: Sub-SCR (€000s) | C3: SCR (€000s) | D3: % of BSCR
A4: COMPONENT SCRs
A5: Health Underwriting Risk | B5: ='Health UW Risk'!D33 -> 85442.917
A6: Market Risk | B6: ='Market Risk'!D26 -> 76242.996
A7: Counterparty Default Risk | B7: ='Credit Risk'!F20 -> 10094.594
A9: BSCR CORRELATION MATRIX (EIOPA Art.304)
B10: Health UW | C10: Market | D10: Credit
A11: Health UW | B11: 1 | C11: 0.25 | D11: 0.25
A12: Market | B12: 0.25 | C12: 1 | D12: 0.25
A13: Credit | B13: 0.25 | C13: 0.25 | D13: 1
A15: SCR CALCULATION
A16: Diversified BSCR (correlation formula) | C16: =SQRT(B5^2+B6^2+B7^2+2*0.25*B5*B6+2*0.25*B5*B7+2*0.25*B6*B7) -> 131486.41
A17: Health Underwriting Risk | B17: =B5 -> 85442.917 | D17: =IF(C16=0,0,B5/C16) -> 0.64982318
A18: Market Risk | B18: =B6 -> 76242.996 | D18: =IF(C16=0,0,B6/C16) -> 0.57985457
A19: Counterparty Default Risk | B19: =B7 -> 10094.594 | D19: =IF(C16=0,0,B7/C16) -> 0.076772906
A21: Adjustment for Loss Absorbing Capacity of TPs | C21: -8000
A22: Adjustment for Loss Absorbing Capacity of DT | C22: -4000
A24: BSCR (after adjustments) | C24: =C16+C21+C22 -> 119486.41
A26: Operational Risk SCR | C26: ='Op Risk'!C14 -> 16656
A28: FINAL SCR & MCR
A30: BSCR (after adjustments) | C30: =C24 -> 119486.41 | D30: =IF(C33=0,0,C30/C33) -> 0.87765752
A31: Operational Risk | C31: ='Op Risk'!C14 -> 16656 | D31: =IF(C33=0,0,C31/C33) -> 0.12234248
A33: Solvency Capital Requirement (SCR) | C33: =C24+C26 -> 136142.41
A38: SCR Total | C38: =C33 -> 136142.41
A40: MINIMUM CAPITAL REQUIREMENT (MCR)
A41: Linear MCR | C41: =C38*0.25 -> 34035.603
A42: MCR Floor (25% of SCR) | C42: =C38*0.25 -> 34035.603 | D42: =C50 -> 0.19097649
A43: MCR Cap (45% of SCR) | C43: =C38*0.45 -> 61264.085
A44: MCR (constrained) | C44: =MIN(MAX(C41,C42),C43) -> 34035.603 | D44: =C44 -> 34035.603
A46: COVERAGE RATIOS
A47: Eligible Own Funds for SCR | C47: ='Own Funds'!C35 -> 26000
A48: Eligible Own Funds for MCR | C48: ='Own Funds'!C31+'Own Funds'!C32 -> 23400
A50: SCR Coverage Ratio | C50: =IF(C38=0,0,C47/C38) -> 0.19097649
A51: MCR Coverage Ratio | C51: =IF(C44=0,0,C48/C44) -> 0.68751537

Sheet ORSA Summary
A1: OWN RISK & SOLVENCY ASSESSMENT (ORSA) – SUMMARY DASHBOARD
A3: STRESS TEST & SCENARIO ANALYSIS
A4: Scenario | B4: SCR Impact (€000s) | C4: Own Funds Impact | D4: Coverage Ratio | E4: RAG Status
A5: Base Case (Current) | B5: ='SCR Summary'!C38+0 -> 136142.41 | C5: ='Own Funds'!C35+(0) -> 26000 | D5: ='SCR Summary'!C42 -> 34035.603 | E5: Green
A6: Pandemic Stress (1-in-200) | B6: ='SCR Summary'!C38+85000 -> 221142.41 | C6: ='Own Funds'!C35+(-42000) -> -16000 | D6: =IF(B6=0,0,C6/B6) -> -0.072351567 | E6: Amber
A7: Market Crash (equity -40%) | B7: ='SCR Summary'!C38+35000 -> 171142.41 | C7: ='Own Funds'!C35+(-30000) -> -4000 | D7: =IF(B7=0,0,C7/B7) -> -0.023372348 | E7: Amber
A8: Interest Rate Spike (+300bps) | B8: ='SCR Summary'!C38+28000 -> 164142.41 | C8: ='Own Funds'!C35+(-18000) -> 8000 | D8: =IF(B8=0,0,C8/B8) -> 0.048738166 | E8: Green
A9: Catastrophic Lapse (+50%) | B9: ='SCR Summary'!C38+22000 -> 158142.41 | C9: ='Own Funds'!C35+(-15000) -> 11000 | D9: =IF(B9=0,0,C9/B9) -> 0.069557559 | E9: Green
A10: Combined Stress | B10: ='SCR Summary'!C38+145000 -> 281142.41 | C10: ='Own Funds'!C35+(-95000) -> -69000 | D10: =IF(B10=0,0,C10/B10) -> -0.24542722 | E10: Red
A11: Reverse Stress Test (threshold) | B11: N/A | C11: N/A | D11: 150% | E11: Monitor
A14: CAPITAL MANAGEMENT ACTIONS & TRIGGERS
A15: Action / Trigger | B15: Coverage Threshold | C15: Current Status | D15: Trigger Met? | E15: Action Owner
A16: Management Warning Level | B16: 160% | C16: ='SCR Summary'!C42 -> 34035.603 | D16: =IF('SCR Summary'!C42<VALUE(LEFT("160%",LEN("160%")-1))/100,"⚠ TRIGGERED","✓ OK") -> ✓ OK | E16: CFO
A17: Board Reporting Escalation | B17: 150% | C17: ='SCR Summary'!C42 -> 34035.603 | D17: =IF('SCR Summary'!C42<VALUE(LEFT("150%",LEN("150%")-1))/100,"⚠ TRIGGERED","✓ OK") -> ✓ OK | E17: Board
A18: Capital Raising Consideration | B18: 140% | C18: ='SCR Summary'!C42 -> 34035.603 | D18: =IF('SCR Summary'!C42<VALUE(LEFT("140%",LEN("140%")-1))/100,"⚠ TRIGGERED","✓ OK") -> ✓ OK | E18: CEO / Board
A19: Regulatory Notification | B19: 130% | C19: ='SCR Summary'!C42 -> 34035.603 | D19: =IF('SCR Summary'!C42<VALUE(LEFT("130%",LEN("130%")-1))/100,"⚠ TRIGGERED","✓ OK") -> ✓ OK | E19: CRO → Regulator
A20: Recovery Plan Activation | B20: 110% | C20: ='SCR Summary'!C42 -> 34035.603 | D20: =IF('SCR Summary'!C42<VALUE(LEFT("110%",LEN("110%")-1))/100,"⚠ TRIGGERED","✓ OK") -> ✓ OK | E20: CEO
A23: ORSA PROCESS CHECKLIST (Art. 45 Solvency II Directive)
A24: ORSA Component | B24: Status | C24: Frequency | D24: Owner
A25: Overall Solvency Needs assessment | B25: Complete | C25: Annual | D25: CRO
A26: Compliance with SCR / MCR assessment | B26: Complete | C26: Quarterly | D26: CFO
A27: Significance of deviation from standard formula | B27: Complete | C27: Annual | D27: Actuarial Fn
A28: Forward-looking assessment (3yr projection) | B28: Complete | C28: Annual | D28: Finance
A29: Stress & scenario testing | B29: Complete | C29: Semi-ann | D29: Risk Fn
A30: Board approval of ORSA report | B30: Pending | C30: Annual | D30: Board
A31: Regulatory submission of ORSA | B31: Pending | C31: Annual | D31: CRO
